Workbook
Name UPDATE: 'Data Sheet'!$E$1

Sheet Profit & Loss
A1: ='Data Sheet'!B1 -> NESTLE INDIA LTD | H1: =UPDATE | M1: SCREENER.IN
A3: Narration | B3: ='Data Sheet'!B16 -> 42735 | C3: ='Data Sheet'!C16 -> 43100 | D3: ='Data Sheet'!D16 -> 43465 | E3: ='Data Sheet'!E16 -> 43830 | F3: ='Data Sheet'!F16 -> 44196 | G3: ='Data Sheet'!G16 -> 44561 | H3: ='Data Sheet'!H16 -> 44926 | I3: ='Data Sheet'!I16 -> 45291 | ... K3: ='Data Sheet'!K16 -> 45747 | L3: Trailing | M3: Best Case | N3: Worst Case
A4: Sales | B4: ='Data Sheet'!B17 -> 9141.34 | C4: ='Data Sheet'!C17 -> 10009.6 | D4: ='Data Sheet'!D17 -> 11292.27 | E4: ='Data Sheet'!E17 -> 12368.9 | F4: ='Data Sheet'!F17 -> 13350.03 | G4: ='Data Sheet'!G17 -> 14740.59 | H4: ='Data Sheet'!H17 -> 16896.96 | I4: ='Data Sheet'!I17 -> 19126.3 | ... K4: ='Data Sheet'!K17 -> 20201.56 | L4: =SUM(Quarters!H4:K4) -> 21910.69 | M4: =$K4+M23*K4 -> 21910.69 | N4: =$K4+N23*L4 -> 21545.789
A5: Expenses | B5: =SUM('Data Sheet'!B18,'Data Sheet'!B20:B24, -1*'Data Sheet'!B19) -> 7291.5 | C5: =SUM('Data Sheet'!C18,'Data Sheet'!C20:C24, -1*'Data Sheet'!C19) -> 7913.07 | D5: =SUM('Data Sheet'!D18,'Data Sheet'!D20:D24, -1*'Data Sheet'!D19) -> 8674.62 | E5: =SUM('Data Sheet'!E18,'Data Sheet'!E20:E24, -1*'Data Sheet'!E19) -> 9443.02 | F5: =SUM('Data Sheet'!F18,'Data Sheet'!F20:F24, -1*'Data Sheet'!F19) -> 10148.53 | G5: =SUM('Data Sheet'!G18,'Data Sheet'!G20:G24, -1*'Data Sheet'!G19) -> 11178.19 | H5: =SUM('Data Sheet'!H18,'Data Sheet'!H20:H24, -1*'Data Sheet'!H19) -> 13190.67 | I5: =SUM('Data Sheet'!I18,'Data Sheet'!I20:I24, -1*'Data Sheet'!I19) -> 14655.31 | ... K5: =SUM('Data Sheet'!K18,'Data Sheet'!K20:K24, -1*'Data Sheet'!K19) -> 15430.23 | L5: =SUM(Quarters!H5:K5) -> 16982.76 | M5: =M4-M6 -> 16723.569 | N5: =N4-N6 -> 16699.929
A6: Operating Profit | B6: =B4-B5 -> 1849.84 | C6: =C4-C5 -> 2096.53 | D6: =D4-D5 -> 2617.65 | E6: =E4-E5 -> 2925.88 | F6: =F4-F5 -> 3201.5 | G6: =G4-G5 -> 3562.4 | H6: =H4-H5 -> 3706.29 | I6: =I4-I5 -> 4470.99 | ... K6: =K4-K5 -> 4771.33 | L6: =SUM(Quarters!H6:K6) -> 4927.93 | M6: =M4*M24 -> 5187.1206 | N6: =N4*N24 -> 4845.8602
A7: Other Income | B7: ='Data Sheet'!B25 -> 140.12 | C7: ='Data Sheet'!C25 -> 176.92 | D7: ='Data Sheet'!D25 -> 258.92 | E7: ='Data Sheet'!E25 -> 246.88 | F7: ='Data Sheet'!F25 -> 145.85 | G7: ='Data Sheet'!G25 -> -112.38 | H7: ='Data Sheet'!H25 -> 107.26 | I7: ='Data Sheet'!I25 -> 115.5 | ... K7: ='Data Sheet'!K25 -> 352.06 | L7: =SUM(Quarters!H7:K7) -> 182.78 | M7: 0 | N7: 0
A8: Depreciation | B8: ='Data Sheet'!B26 -> 353.67 | C8: ='Data Sheet'!C26 -> 342.25 | D8: ='Data Sheet'!D26 -> 335.67 | E8: ='Data Sheet'!E26 -> 370.15 | F8: ='Data Sheet'!F26 -> 370.38 | G8: ='Data Sheet'!G26 -> 391.02 | H8: ='Data Sheet'!H26 -> 403.01 | I8: ='Data Sheet'!I26 -> 428.91 | ... K8: ='Data Sheet'!K26 -> 539.92 | L8: =SUM(Quarters!H8:K8) -> 650.04 | M8: =+$L8 -> 650.04 | N8: =+$L8 -> 650.04
A9: Interest | B9: ='Data Sheet'!B27 -> 90.91 | C9: ='Data Sheet'!C27 -> 91.9 | D9: ='Data Sheet'!D27 -> 111.95 | E9: ='Data Sheet'!E27 -> 129.12 | F9: ='Data Sheet'!F27 -> 164.18 | G9: ='Data Sheet'!G27 -> 201.68 | H9: ='Data Sheet'!H27 -> 154.57 | I9: ='Data Sheet'!I27 -> 119.29 | ... K9: ='Data Sheet'!K27 -> 136 | L9: =SUM(Quarters!H9:K9) -> 159.05 | M9: =+$L9 -> 159.05 | N9: =+$L9 -> 159.05
A10: Profit before tax | B10: ='Data Sheet'!B28 -> 1545.38 | C10: ='Data Sheet'!C28 -> 1839.3 | D10: ='Data Sheet'!D28 -> 2428.95 | E10: ='Data Sheet'!E28 -> 2673.49 | F10: ='Data Sheet'!F28 -> 2812.79 | G10: ='Data Sheet'!G28 -> 2857.32 | H10: ='Data Sheet'!H28 -> 3255.97 | I10: ='Data Sheet'!I28 -> 4038.29 | ... K10: ='Data Sheet'!K28 -> 4447.47 | L10: =SUM(Quarters!H10:K10) -> 4301.62 | M10: =M6+M7-SUM(M8:M9) -> 4378.0306 | N10: =N6+N7-SUM(N8:N9) -> 4036.7702
A11: Tax | B11: ='Data Sheet'!B29 -> 544.02 | C11: ='Data Sheet'!C29 -> 614.11 | D11: ='Data Sheet'!D29 -> 822.02 | E11: ='Data Sheet'!E29 -> 705.05 | F11: ='Data Sheet'!F29 -> 730.36 | G11: ='Data Sheet'!G29 -> 738.91 | H11: ='Data Sheet'!H29 -> 865.45 | I11: ='Data Sheet'!I29 -> 1039.62 | ... K11: ='Data Sheet'!K29 -> 1132.97 | L11: =SUM(Quarters!H11:K11) -> 985.72 | M11: =IF($L10>0,$L11/$L10,0) -> 0.22915088 | N11: =IF($L10>0,$L11/$L10,0) -> 0.22915088
A12: Net profit | B12: ='Data Sheet'!B30 -> 1001.36 | C12: ='Data Sheet'!C30 -> 1225.19 | D12: ='Data Sheet'!D30 -> 1606.93 | E12: ='Data Sheet'!E30 -> 1968.44 | F12: ='Data Sheet'!F30 -> 2082.43 | G12: ='Data Sheet'!G30 -> 2118.41 | H12: ='Data Sheet'!H30 -> 2390.52 | I12: ='Data Sheet'!I30 -> 2998.67 | ... K12: ='Data Sheet'!K30 -> 3314.5 | L12: =SUM(Quarters!H12:K12) -> 3315.9 | M12: =M10-M11*M10 -> 3374.801 | N12: =N10-N11*N10 -> 3111.7407
A13: EPS | B13: =IF('Data Sheet'!B93>0,B12/'Data Sheet'!B93,0) -> 5.1937759 | C13: =IF('Data Sheet'!C93>0,C12/'Data Sheet'!C93,0) -> 6.3547199 | D13: =IF('Data Sheet'!D93>0,D12/'Data Sheet'!D93,0) -> 8.3346992 | E13: =IF('Data Sheet'!E93>0,E12/'Data Sheet'!E93,0) -> 10.209751 | F13: =IF('Data Sheet'!F93>0,F12/'Data Sheet'!F93,0) -> 10.800985 | G13: =IF('Data Sheet'!G93>0,G12/'Data Sheet'!G93,0) -> 10.987604 | H13: =IF('Data Sheet'!H93>0,H12/'Data Sheet'!H93,0) -> 12.398963 | I13: =IF('Data Sheet'!I93>0,I12/'Data Sheet'!I93,0) -> 15.553268 | ... K13: =IF('Data Sheet'!K93>0,K12/'Data Sheet'!K93,0) -> 17.188715 | L13: =IF('Data Sheet'!$B6>0,'Profit & Loss'!L12/'Data Sheet'!$B6,0) -> 17.195848 | M13: =IF('Data Sheet'!$B6>0,'Profit & Loss'!M12/'Data Sheet'!$B6,0) -> 17.501302 | N13: =IF('Data Sheet'!$B6>0,'Profit & Loss'!N12/'Data Sheet'!$B6,0) -> 16.137104
A14: Price to earning | B14: =IF(B15>0,B15/B13,"") -> 58.034849 | C14: =IF(C15>0,C15/C13,"") -> 61.930345 | D14: =IF(D15>0,D15/D13,"") -> 66.497901 | E14: =IF(E15>0,E15/E13,"") -> 72.40823 | F14: =IF(F15>0,F15/F13,"") -> 85.132047 | G14: =IF(G15>0,G15/G13,"") -> 89.672874 | H14: =IF(H15>0,H15/H13,"") -> 79.063066 | I14: =IF(I15>0,I15/I13,"") -> 85.449568 | ... K14: =IF(K15>0,K15/K13,"") -> 65.472025 | L14: =IF(L13>0,L15/L13,0) -> 73.235701 | M14: =M25 -> 73.235701 | N14: =N25 -> 72.11135
A15: Price | B15: ='Data Sheet'!B90 -> 301.42 | C15: ='Data Sheet'!C90 -> 393.55 | D15: ='Data Sheet'!D90 -> 554.24 | E15: ='Data Sheet'!E90 -> 739.27 | F15: ='Data Sheet'!F90 -> 919.51 | G15: ='Data Sheet'!G90 -> 985.29 | H15: ='Data Sheet'!H90 -> 980.3 | I15: ='Data Sheet'!I90 -> 1329.02 | ... K15: ='Data Sheet'!K90 -> 1125.38 | L15: ='Data Sheet'!B8 -> 1259.35 | M15: =M13*M14 -> 1281.7201 | N15: =N13*N14 -> 1163.6683
A17: RATIOS:
A18: Dividend Payout | B18: =IF('Data Sheet'!B30>0, 'Data Sheet'!B31/'Data Sheet'!B30, 0) -> 0.60662499 | C18: =IF('Data Sheet'!C30>0, 'Data Sheet'!C31/'Data Sheet'!C30, 0) -> 0.67680115 | D18: =IF('Data Sheet'!D30>0, 'Data Sheet'!D31/'Data Sheet'!D30, 0) -> 0.69003006 | E18: =IF('Data Sheet'!E30>0, 'Data Sheet'!E31/'Data Sheet'!E30, 0) -> 1.6752149 | F18: =IF('Data Sheet'!F30>0, 'Data Sheet'!F31/'Data Sheet'!F30, 0) -> 0.92603353 | G18: =IF('Data Sheet'!G30>0, 'Data Sheet'!G31/'Data Sheet'!G30, 0) -> 0.91030537 | H18: =IF('Data Sheet'!H30>0, 'Data Sheet'!H31/'Data Sheet'!H30, 0) -> 0.88735505 | I18: =IF('Data Sheet'!I30>0, 'Data Sheet'!I31/'Data Sheet'!I30, 0) -> 0.5594847 | ... K18: =IF('Data Sheet'!K30>0, 'Data Sheet'!K31/'Data Sheet'!K30, 0) -> 0.78543973
A19: OPM | B19: =IF(B6>0,B6/B4,0) -> 0.20235983 | C19: =IF(C6>0,C6/C4,0) -> 0.20945193 | D19: =IF(D6>0,D6/D4,0) -> 0.23180902 | E19: =IF(E6>0,E6/E4,0) -> 0.23655135 | F19: =IF(F6>0,F6/F4,0) -> 0.2398122 | G19: =IF(G6>0,G6/G4,0) -> 0.24167282 | H19: =IF(H6>0,H6/H4,0) -> 0.21934656 | I19: =IF(I6>0,I6/I4,0) -> 0.23376137 | ... L19: =IF(L6>0,L6/L4,0) -> 0.22490985
G22: TRENDS: | H22: 10 YEARS | I22: 7 YEARS | J22: 5 YEARS | K22: 3 YEARS | L22: RECENT | M22: BEST | N22: WORST
G23: Sales Growth | H23: =IF(B4=0,"",POWER($K4/B4,1/9)-1) -> 0.092103739 | I23: =IF(D4=0,"",POWER($K4/D4,1/7)-1) -> 0.086641373 | J23: =IF(F4=0,"",POWER($K4/F4,1/5)-1) -> 0.086376927 | K23: =IF(H4=0,"",POWER($K4/H4, 1/3)-1) -> 0.061350374 | L23: =IF(ISERROR(MAX(IF(J4=0,"",(K4-J4)/J4),IF(K4=0,"",(L4-K4)/K4))),"",MAX(IF(J4=0,"",(K4-J4)/J4),IF(K4=0,"",(L4-K4)/K4))) -> 0.084603862 | M23: =MAX(K23:L23) -> 0.084603862 | N23: =MIN(H23:L23) -> 0.061350374
G24: OPM | H24: =IF(SUM(B4:$K$4)=0,"",SUMPRODUCT(B19:$K$19,B4:$K$4)/SUM(B4:$K$4)) -> 0.2312909 | I24: =IF(SUM(E4:$K$4)=0,"",SUMPRODUCT(E19:$K$19,E4:$K$4)/SUM(E4:$K$4)) -> 0.2352323 | J24: =IF(SUM(G4:$K$4)=0,"",SUMPRODUCT(G19:$K$19,G4:$K$4)/SUM(G4:$K$4)) -> 0.23442003 | K24: =IF(SUM(I4:$K$4)=0, "", SUMPRODUCT(I19:$K$19,I4:$K$4)/SUM(I4:$K$4)) -> 0.23673926 | L24: =L19 -> 0.22490985 | M24: =MAX(K24:L24) -> 0.23673926 | N24: =MIN(H24:L24) -> 0.22490985
G25: Price to Earning | H25: =IF(ISERROR(AVERAGEIF(B14:$L14,">0")),"",AVERAGEIF(B14:$L14,">0")) -> 72.834974 | I25: =IF(ISERROR(AVERAGEIF(E14:$L14,">0")),"",AVERAGEIF(E14:$L14,">0")) -> 76.840202 | J25: =IF(ISERROR(AVERAGEIF(G14:$L14,">0")),"",AVERAGEIF(G14:$L14,">0")) -> 76.19689 | K25: =IF(ISERROR(AVERAGEIF(I14:$L14,">0")),"",AVERAGEIF(I14:$L14,">0")) -> 72.11135 | L25: =L14 -> 73.235701 | M25: =MAX(K25:L25) -> 73.235701 | N25: =MIN(H25:L25) -> 72.11135

Sheet Quarters
A1: ='Profit & Loss'!A1 -> NESTLE INDIA LTD | E1: =UPDATE | J1: SCREENER.IN
A3: Narration | B3: ='Data Sheet'!B41 -> 45199 | C3: ='Data Sheet'!C41 -> 45291 | D3: ='Data Sheet'!D41 -> 45382 | E3: ='Data Sheet'!E41 -> 45473 | F3: ='Data Sheet'!F41 -> 45565 | G3: ='Data Sheet'!G41 -> 45657 | H3: ='Data Sheet'!H41 -> 45747 | I3: ='Data Sheet'!I41 -> 45838 | ... K3: ='Data Sheet'!K41 -> 46022
A4: Sales | B4: ='Data Sheet'!B42 -> 5036.82 | C4: ='Data Sheet'!C42 -> 4600.42 | D4: ='Data Sheet'!D42 -> 5267.59 | E4: ='Data Sheet'!E42 -> 4813.95 | F4: ='Data Sheet'!F42 -> 5104 | G4: ='Data Sheet'!G42 -> 4779.73 | H4: ='Data Sheet'!H42 -> 5503.88 | I4: ='Data Sheet'!I42 -> 5096.16 | ... K4: ='Data Sheet'!K42 -> 5667.04
A5: Expenses | B5: ='Data Sheet'!B43 -> 3811.95 | C5: ='Data Sheet'!C43 -> 3505.3 | D5: ='Data Sheet'!D43 -> 3917.54 | E5: ='Data Sheet'!E43 -> 3699.62 | F5: ='Data Sheet'!F43 -> 3936.27 | G5: ='Data Sheet'!G43 -> 3677.04 | H5: ='Data Sheet'!H43 -> 4114.92 | I5: ='Data Sheet'!I43 -> 3995.9 | ... K5: ='Data Sheet'!K43 -> 4464.97
A6: Operating Profit | B6: ='Data Sheet'!B50 -> 1224.87 | C6: ='Data Sheet'!C50 -> 1095.12 | D6: ='Data Sheet'!D50 -> 1350.05 | E6: ='Data Sheet'!E50 -> 1114.33 | F6: ='Data Sheet'!F50 -> 1167.73 | G6: ='Data Sheet'!G50 -> 1102.69 | H6: ='Data Sheet'!H50 -> 1388.96 | I6: ='Data Sheet'!I50 -> 1100.26 | ... K6: ='Data Sheet'!K50 -> 1202.07
A7: Other Income | B7: ='Data Sheet'!B44 -> 139.69 | C7: ='Data Sheet'!C44 -> -77 | D7: ='Data Sheet'!D44 -> 36.83 | E7: ='Data Sheet'!E44 -> 39.12 | F7: ='Data Sheet'!F44 -> 297.68 | G7: ='Data Sheet'!G44 -> 4.44 | H7: ='Data Sheet'!H44 -> 8.44 | I7: ='Data Sheet'!I44 -> 4.04 | ... K7: ='Data Sheet'!K44 -> 168.66
A8: Depreciation | B8: ='Data Sheet'!B45 -> 111.16 | C8: ='Data Sheet'!C45 -> 108.69 | D8: ='Data Sheet'!D45 -> 110.1 | E8: ='Data Sheet'!E45 -> 112.71 | F8: ='Data Sheet'!F45 -> 121.6 | G8: ='Data Sheet'!G45 -> 150.27 | H8: ='Data Sheet'!H45 -> 155.34 | I8: ='Data Sheet'!I45 -> 156.94 | ... K8: ='Data Sheet'!K45 -> 174.41
A9: Interest | B9: ='Data Sheet'!B46 -> 31.38 | C9: ='Data Sheet'!C46 -> 22.95 | D9: ='Data Sheet'!D46 -> 26.2 | E9: ='Data Sheet'!E46 -> 31.68 | F9: ='Data Sheet'!F46 -> 32.22 | G9: ='Data Sheet'!G46 -> 34.6 | H9: ='Data Sheet'!H46 -> 37.5 | I9: ='Data Sheet'!I46 -> 46.89 | ... K9: ='Data Sheet'!K46 -> 28.25
A10: Profit before tax | B10: ='Data Sheet'!B47 -> 1222.02 | C10: ='Data Sheet'!C47 -> 886.48 | D10: ='Data Sheet'!D47 -> 1250.58 | E10: ='Data Sheet'!E47 -> 1009.06 | F10: ='Data Sheet'!F47 -> 1311.59 | G10: ='Data Sheet'!G47 -> 922.26 | H10: ='Data Sheet'!H47 -> 1204.56 | I10: ='Data Sheet'!I47 -> 900.47 | ... K10: ='Data Sheet'!K47 -> 1168.07
A11: Tax | B11: ='Data Sheet'!B48 -> 313.94 | C11: ='Data Sheet'!C48 -> 230.87 | D11: ='Data Sheet'!D48 -> 316.41 | E11: ='Data Sheet'!E48 -> 262.46 | F11: ='Data Sheet'!F48 -> 325.23 | G11: ='Data Sheet'!G48 -> 226.13 | H11: ='Data Sheet'!H48 -> 319.15 | I11: ='Data Sheet'!I48 -> 241.24 | ... K11: ='Data Sheet'!K48 -> 150.01
A12: Net profit | B12: ='Data Sheet'!B49 -> 908.08 | C12: ='Data Sheet'!C49 -> 655.61 | D12: ='Data Sheet'!D49 -> 934.17 | E12: ='Data Sheet'!E49 -> 746.6 | F12: ='Data Sheet'!F49 -> 986.36 | G12: ='Data Sheet'!G49 -> 696.13 | H12: ='Data Sheet'!H49 -> 885.41 | I12: ='Data Sheet'!I49 -> 659.23 | ... K12: ='Data Sheet'!K49 -> 1018.06
A14: OPM | B14: =IF(B4>0,B6/B4,"") -> 0.2431832 | C14: =IF(C4>0,C6/C4,"") -> 0.23804783 | D14: =IF(D4>0,D6/D4,"") -> 0.25629368 | E14: =IF(E4>0,E6/E4,"") -> 0.23147935 | F14: =IF(F4>0,F6/F4,"") -> 0.22878723 | G14: =IF(G4>0,G6/G4,"") -> 0.23070132 | H14: =IF(H4>0,H6/H4,"") -> 0.25236015 | I14: =IF(I4>0,I6/I4,"") -> 0.21589981 | ... K14: =IF(K4>0,K6/K4,"") -> 0.21211603

Sheet Balance Sheet
A1: ='Profit & Loss'!A1 -> NESTLE INDIA LTD | E1: =UPDATE | J1: SCREENER.IN
A3: Narration | B3: ='Data Sheet'!B56 -> 42735 | C3: ='Data Sheet'!C56 -> 43100 | D3: ='Data Sheet'!D56 -> 43465 | E3: ='Data Sheet'!E56 -> 43830 | F3: ='Data Sheet'!F56 -> 44196 | G3: ='Data Sheet'!G56 -> 44561 | H3: ='Data Sheet'!H56 -> 44926 | I3: ='Data Sheet'!I56 -> 45291 | ... K3: ='Data Sheet'!K56 -> 45747
A4: Equity Share Capital | B4: ='Data Sheet'!B57 -> 96.42 | C4: ='Data Sheet'!C57 -> 96.42 | D4: ='Data Sheet'!D57 -> 96.42 | E4: ='Data Sheet'!E57 -> 96.42 | F4: ='Data Sheet'!F57 -> 96.42 | G4: ='Data Sheet'!G57 -> 96.42 | H4: ='Data Sheet'!H57 -> 96.42 | I4: ='Data Sheet'!I57 -> 96.42 | ... K4: ='Data Sheet'!K57 -> 96.42
A5: Reserves | B5: ='Data Sheet'!B58 -> 3185.91 | C5: ='Data Sheet'!C58 -> 3324.17 | D5: ='Data Sheet'!D58 -> 3577.32 | E5: ='Data Sheet'!E58 -> 1822.45 | F5: ='Data Sheet'!F58 -> 1922.92 | G5: ='Data Sheet'!G58 -> 1849.96 | H5: ='Data Sheet'!H58 -> 2362.75 | I5: ='Data Sheet'!I58 -> 2362.75 | ... K5: ='Data Sheet'!K58 -> 4020.73
A6: Borrowings | B6: ='Data Sheet'!B59 -> 33.15 | C6: ='Data Sheet'!C59 -> 35.14 | D6: ='Data Sheet'!D59 -> 35.14 | E6: ='Data Sheet'!E59 -> 188.94 | F6: ='Data Sheet'!F59 -> 147.49 | G6: ='Data Sheet'!G59 -> 266.46 | H6: ='Data Sheet'!H59 -> 270.52 | I6: ='Data Sheet'!I59 -> 270.52 | ... K6: ='Data Sheet'!K59 -> 1166.85
A7: Other Liabilities | B7: ='Data Sheet'!B60 -> 3494.98 | C7: ='Data Sheet'!C60 -> 3906.86 | D7: ='Data Sheet'!D60 -> 4379.2 | E7: ='Data Sheet'!E60 -> 5065.13 | F7: ='Data Sheet'!F60 -> 5732.9 | G7: ='Data Sheet'!G60 -> 6021.29 | H7: ='Data Sheet'!H60 -> 6249.05 | I7: ='Data Sheet'!I60 -> 6249.05 | ... K7: ='Data Sheet'!K60 -> 7039.89
A8: Total | B8: ='Data Sheet'!B61 -> 6810.46 | C8: ='Data Sheet'!C61 -> 7362.59 | D8: ='Data Sheet'!D61 -> 8088.08 | E8: ='Data Sheet'!E61 -> 7172.94 | F8: ='Data Sheet'!F61 -> 7899.73 | G8: ='Data Sheet'!G61 -> 8234.13 | H8: ='Data Sheet'!H61 -> 8978.74 | I8: ='Data Sheet'!I61 -> 8978.74 | ... K8: ='Data Sheet'!K61 -> 12323.89
A10: Net Block | B10: ='Data Sheet'!B62 -> 2730.14 | C10: ='Data Sheet'!C62 -> 2616.18 | D10: ='Data Sheet'!D62 -> 2400.62 | E10: ='Data Sheet'!E62 -> 2341.45 | F10: ='Data Sheet'!F62 -> 2179.41 | G10: ='Data Sheet'!G62 -> 2994.67 | H10: ='Data Sheet'!H62 -> 3043.7 | I10: ='Data Sheet'!I62 -> 3043.7 | ... K10: ='Data Sheet'!K62 -> 5473.61
A11: Capital Work in Progress | B11: ='Data Sheet'!B63 -> 188.17 | C11: ='Data Sheet'!C63 -> 94.16 | D11: ='Data Sheet'!D63 -> 105.2 | E11: ='Data Sheet'!E63 -> 143.3 | F11: ='Data Sheet'!F63 -> 638.58 | G11: ='Data Sheet'!G63 -> 246.23 | H11: ='Data Sheet'!H63 -> 358.36 | I11: ='Data Sheet'!I63 -> 358.36 | ... K11: ='Data Sheet'!K63 -> 1172.56
A12: Investments | B12: ='Data Sheet'!B64 -> 1755.66 | C12: ='Data Sheet'!C64 -> 1978.87 | D12: ='Data Sheet'!D64 -> 2658.49 | E12: ='Data Sheet'!E64 -> 1751.05 | F12: ='Data Sheet'!F64 -> 1463.77 | G12: ='Data Sheet'!G64 -> 773.98 | H12: ='Data Sheet'!H64 -> 777.54 | I12: ='Data Sheet'!I64 -> 777.54 | ... K12: ='Data Sheet'!K64 -> 705.6
A13: Other Assets | B13: ='Data Sheet'!B65 -> 2136.49 | C13: ='Data Sheet'!C65 -> 2673.38 | D13: ='Data Sheet'!D65 -> 2923.77 | E13: ='Data Sheet'!E65 -> 2937.14 | F13: ='Data Sheet'!F65 -> 3617.97 | G13: ='Data Sheet'!G65 -> 4219.25 | H13: ='Data Sheet'!H65 -> 4799.14 | I13: ='Data Sheet'!I65 -> 4799.14 | ... K13: ='Data Sheet'!K65 -> 4972.12
A14: Total | B14: ='Data Sheet'!B66 -> 6810.46 | C14: ='Data Sheet'!C66 -> 7362.59 | D14: ='Data Sheet'!D66 -> 8088.08 | E14: ='Data Sheet'!E66 -> 7172.94 | F14: ='Data Sheet'!F66 -> 7899.73 | G14: ='Data Sheet'!G66 -> 8234.13 | H14: ='Data Sheet'!H66 -> 8978.74 | I14: ='Data Sheet'!I66 -> 8978.74 | ... K14: ='Data Sheet'!K66 -> 12323.89
A16: Working Capital | B16: =B13-B7 -> -1358.49 | C16: =C13-C7 -> -1233.48 | D16: =D13-D7 -> -1455.43 | E16: =E13-E7 -> -2127.99 | F16: =F13-F7 -> -2114.93 | G16: =G13-G7 -> -1802.04 | H16: =H13-H7 -> -1449.91 | I16: =I13-I7 -> -1449.91 | ... K16: =K13-K7 -> -2067.77
A17: Debtors | B17: ='Data Sheet'!B67 -> 97.93 | C17: ='Data Sheet'!C67 -> 88.97 | D17: ='Data Sheet'!D67 -> 124.59 | E17: ='Data Sheet'!E67 -> 124.33 | F17: ='Data Sheet'!F67 -> 164.93 | G17: ='Data Sheet'!G67 -> 165.97 | H17: ='Data Sheet'!H67 -> 191.89 | I17: ='Data Sheet'!I67 -> 191.89 | ... K17: ='Data Sheet'!K67 -> 363.15
A18: Inventory | B18: ='Data Sheet'!B68 -> 940.06 | C18: ='Data Sheet'!C68 -> 902.47 | D18: ='Data Sheet'!D68 -> 965.55 | E18: ='Data Sheet'!E68 -> 1283.07 | F18: ='Data Sheet'!F68 -> 1416.48 | G18: ='Data Sheet'!G68 -> 1592.65 | H18: ='Data Sheet'!H68 -> 1928.77 | I18: ='Data Sheet'!I68 -> 1928.77 | ... K18: ='Data Sheet'!K68 -> 2850.14
A20: Debtor Days | B20: =IF('Profit & Loss'!B4>0,'Balance Sheet'!B17/('Profit & Loss'!B4/365),0) -> 3.9101981 | C20: =IF('Profit & Loss'!C4>0,'Balance Sheet'!C17/('Profit & Loss'!C4/365),0) -> 3.2442905 | D20: =IF('Profit & Loss'!D4>0,'Balance Sheet'!D17/('Profit & Loss'!D4/365),0) -> 4.0271221 | E20: =IF('Profit & Loss'!E4>0,'Balance Sheet'!E17/('Profit & Loss'!E4/365),0) -> 3.6689156 | F20: =IF('Profit & Loss'!F4>0,'Balance Sheet'!F17/('Profit & Loss'!F4/365),0) -> 4.509312 | G20: =IF('Profit & Loss'!G4>0,'Balance Sheet'!G17/('Profit & Loss'!G4/365),0) -> 4.1096761 | H20: =IF('Profit & Loss'!H4>0,'Balance Sheet'!H17/('Profit & Loss'!H4/365),0) -> 4.1451155 | I20: =IF('Profit & Loss'!I4>0,'Balance Sheet'!I17/('Profit & Loss'!I4/365),0) -> 3.6619655 | ... K20: =IF('Profit & Loss'!K4>0,'Balance Sheet'!K17/('Profit & Loss'!K4/365),0) -> 6.5613621
A21: Inventory Turnover | B21: =IF('Balance Sheet'!B18>0,'Profit & Loss'!B4/'Balance Sheet'!B18,0) -> 9.7242091 | C21: =IF('Balance Sheet'!C18>0,'Profit & Loss'!C4/'Balance Sheet'!C18,0) -> 11.091338 | D21: =IF('Balance Sheet'!D18>0,'Profit & Loss'!D4/'Balance Sheet'!D18,0) -> 11.695169 | E21: =IF('Balance Sheet'!E18>0,'Profit & Loss'!E4/'Balance Sheet'!E18,0) -> 9.640082 | F21: =IF('Balance Sheet'!F18>0,'Profit & Loss'!F4/'Balance Sheet'!F18,0) -> 9.4247924 | G21: =IF('Balance Sheet'!G18>0,'Profit & Loss'!G4/'Balance Sheet'!G18,0) -> 9.2553857 | H21: =IF('Balance Sheet'!H18>0,'Profit & Loss'!H4/'Balance Sheet'!H18,0) -> 8.7604847 | I21: =IF('Balance Sheet'!I18>0,'Profit & Loss'!I4/'Balance Sheet'!I18,0) -> 9.9163197 | ... K21: =IF('Balance Sheet'!K18>0,'Profit & Loss'!K4/'Balance Sheet'!K18,0) -> 7.0879185
A23: Return on Equity | B23: =IF(SUM('Balance Sheet'!B4:B5)>0,'Profit & Loss'!B12/SUM('Balance Sheet'!B4:B5),"") -> 0.30507597 | C23: =IF(SUM('Balance Sheet'!C4:C5)>0,'Profit & Loss'!C12/SUM('Balance Sheet'!C4:C5),"") -> 0.3581809 | D23: =IF(SUM('Balance Sheet'!D4:D5)>0,'Profit & Loss'!D12/SUM('Balance Sheet'!D4:D5),"") -> 0.43740983 | E23: =IF(SUM('Balance Sheet'!E4:E5)>0,'Profit & Loss'!E12/SUM('Balance Sheet'!E4:E5),"") -> 1.0258329 | F23: =IF(SUM('Balance Sheet'!F4:F5)>0,'Profit & Loss'!F12/SUM('Balance Sheet'!F4:F5),"") -> 1.0312429 | G23: =IF(SUM('Balance Sheet'!G4:G5)>0,'Profit & Loss'!G12/SUM('Balance Sheet'!G4:G5),"") -> 1.0883846 | H23: =IF(SUM('Balance Sheet'!H4:H5)>0,'Profit & Loss'!H12/SUM('Balance Sheet'!H4:H5),"") -> 0.97208408 | I23: =IF(SUM('Balance Sheet'!I4:I5)>0,'Profit & Loss'!I12/SUM('Balance Sheet'!I4:I5),"") -> 1.219383 | ... K23: =IF(SUM('Balance Sheet'!K4:K5)>0,'Profit & Loss'!K12/SUM('Balance Sheet'!K4:K5),"") -> 0.80504718
A24: Return on Capital Emp | C24: =IF((B4+B5+B6+C4+C5+C6)>0,('Profit & Loss'!C10+'Profit & Loss'!C9)*2/(B4+B5+B6+C4+C5+C6),"") -> 0.57041504 | D24: =IF((C4+C5+C6+D4+D5+D6)>0,('Profit & Loss'!D10+'Profit & Loss'!D9)*2/(C4+C5+C6+D4+D5+D6),"") -> 0.70929192 | E24: =IF((D4+D5+D6+E4+E5+E6)>0,('Profit & Loss'!E10+'Profit & Loss'!E9)*2/(D4+D5+D6+E4+E5+E6),"") -> 0.96364427 | F24: =IF((E4+E5+E6+F4+F5+F6)>0,('Profit & Loss'!F10+'Profit & Loss'!F9)*2/(E4+E5+E6+F4+F5+F6),"") -> 1.3928518 | G24: =IF((F4+F5+F6+G4+G5+G6)>0,('Profit & Loss'!G10+'Profit & Loss'!G9)*2/(F4+F5+F6+G4+G5+G6),"") -> 1.3969089 | H24: =IF((G4+G5+G6+H4+H5+H6)>0,('Profit & Loss'!H10+'Profit & Loss'!H9)*2/(G4+G5+G6+H4+H5+H6),"") -> 1.3800786 | I24: =IF((H4+H5+H6+I4+I5+I6)>0,('Profit & Loss'!I10+'Profit & Loss'!I9)*2/(H4+H5+H6+I4+I5+I6),"") -> 1.523096 | J24: =IF((I4+I5+I6+J4+J5+J6)>0,('Profit & Loss'!J10+'Profit & Loss'!J9)*2/(I4+I5+I6+J4+J5+J6),"") -> 1.6942375 | K24: =IF((J4+J5+J6+K4+K5+K6)>0,('Profit & Loss'!K10+'Profit & Loss'!K9)*2/(J4+J5+J6+K4+K5+K6),"") -> 1.0220215

Sheet Cash Flow
A1: ='Balance Sheet'!A1 -> NESTLE INDIA LTD | E1: =UPDATE | J1: SCREENER.IN
A3: Narration | B3: ='Data Sheet'!B81 -> 42735 | C3: ='Data Sheet'!C81 -> 43100 | D3: ='Data Sheet'!D81 -> 43465 | E3: ='Data Sheet'!E81 -> 43830 | F3: ='Data Sheet'!F81 -> 44196 | G3: ='Data Sheet'!G81 -> 44561 | H3: ='Data Sheet'!H81 -> 44926 | I3: ='Data Sheet'!I81 -> 45291 | ... K3: ='Data Sheet'!K81 -> 45747
A4: Cash from Operating Activity | B4: ='Data Sheet'!B82 -> 1465.91 | C4: ='Data Sheet'!C82 -> 1817.79 | D4: ='Data Sheet'!D82 -> 2052.45 | E4: ='Data Sheet'!E82 -> 2295.25 | F4: ='Data Sheet'!F82 -> 2454.48 | G4: ='Data Sheet'!G82 -> 2236 | H4: ='Data Sheet'!H82 -> 2737.43 | I4: ='Data Sheet'!I82 -> 3392.19 | ... K4: ='Data Sheet'!K82 -> 2936.35
A5: Cash from Investing Activity | B5: ='Data Sheet'!B83 -> -125.9 | C5: ='Data Sheet'!C83 -> -130.56 | D5: ='Data Sheet'!D83 -> -52.41 | E5: ='Data Sheet'!E83 -> 82.99 | F5: ='Data Sheet'!F83 -> -321.46 | G5: ='Data Sheet'!G83 -> -1920.33 | H5: ='Data Sheet'!H83 -> -391.73 | I5: ='Data Sheet'!I83 -> -926.99 | ... K5: ='Data Sheet'!K83 -> -1810.9
A6: Cash from Financing Activity | B6: ='Data Sheet'!B84 -> -665.61 | C6: ='Data Sheet'!C84 -> -996.62 | D6: ='Data Sheet'!D84 -> -1317.42 | E6: ='Data Sheet'!E84 -> -3601.53 | F6: ='Data Sheet'!F84 -> -1955.89 | G6: ='Data Sheet'!G84 -> -2019.97 | H6: ='Data Sheet'!H84 -> -2122.74 | I6: ='Data Sheet'!I84 -> -2436.47 | ... K6: ='Data Sheet'!K84 -> -1848.12
A7: Net Cash Flow | B7: ='Data Sheet'!B85 -> 674.4 | C7: ='Data Sheet'!C85 -> 690.61 | D7: ='Data Sheet'!D85 -> 682.62 | E7: ='Data Sheet'!E85 -> -1223.29 | F7: ='Data Sheet'!F85 -> 177.13 | G7: ='Data Sheet'!G85 -> -1704.3 | H7: ='Data Sheet'!H85 -> 222.96 | I7: ='Data Sheet'!I85 -> 28.73 | ... K7: ='Data Sheet'!K85 -> -722.67

Sheet Customization
A1: How to use it?
A3: You can customize this workbook as you want.
B4: You can add custom formating, add conditional formating, add your own formulas… do ANYTHING.
B5: Please don't edit the "Data Sheet" only.
A7: After customization, you can upload this back on Screener.
B8: Upload on: | C8: https://www.screener.in/excel/
A10: Download your customized workbooks now onwards.
B11: Now whenever you will "Export to excel" from Screener, it will export your customized file.
A14: TESTING:
B15: This is a testing feature currently.
B16: You can report any formula errors on the worksheet at: support@screener.in

Sheet cash flows
A2: Cash Flows
A3: Standalone Figures in Rs. Crores / View Consolidated
B4: 41974 | C4: 42339 | D4: 42705 | E4: 43070 | F4: 43435 | G4: 43800 | H4: 44166 | I4: 44531 | J4: 44896 | K4: 45261 | L4: 45352 | M4: 45717
A5: Cash from Operating Activity - | B5: 1644 | C5: 1098 | D5: 1466 | E5: 1818 | F5: 2052 | G5: 2295 | H5: 2454 | I5: 2236 | J5: 2737 | K5: 3392 | L5: 4175 | M5: 2936
A6: Profit from operations | B6: 2051 | C6: 1109 | D6: 1765 | E6: 2047 | F6: 2521 | G6: 2805 | H6: 3061 | I6: 3136 | J6: 3609 | K6: 4388 | L6: 5722 | M6: 4672
A7: Receivables | B7: -14 | C7: 21 | D7: -19 | E7: 8 | F7: -36 | G7: 0 | H7: -42 | I7: -2 | J7: -28 | K7: -11 | L7: -109 | M7: -70
A8: Inventory | B8: -108 | C8: 23 | D8: -119 | E8: 38 | F8: -63 | G8: -318 | H8: -133 | I8: -169 | J8: -336 | K8: 56 | L8: -161 | M8: -767
A9: Payables | B9: 118 | C9: 79 | D9: 50 | E9: 185 | F9: 257 | G9: 253 | H9: 23 | I9: 217 | J9: 178 | K9: 68 | L9: 310 | M9: 134
A10: Loans Advances | B10: 34 | C10: -3 | D10: 0 | E10: 0 | F10: 0 | G10: 0 | H10: 0 | I10: -40 | J10: -30 | K10: -30 | L10: -21 | M10: -199
A11: Operating borrowings | B11: 0 | C11: 2 | D11: 0 | E11: 0 | F11: 0 | G11: 0 | H11: 0 | I11: 0 | J11: 0 | K11: 0 | L11: 0 | M11: 0
A12: Other WC items | B12: 153 | C12: 210 | D12: 293 | E12: 144 | F12: 255 | G12: 227 | H12: 249 | I12: -179 | J12: 185 | K12: -19 | L12: -268 | M12: 191
A13: Working capital changes | B13: 182 | C13: 332 | D13: 204 | E13: 375 | F13: 413 | G13: 163 | H13: 97 | I13: -172 | J13: -30 | K13: 63 | L13: -249 | M13: -711
A14: Direct taxes | B14: -589 | C14: -342 | D14: -503 | E14: -604 | F14: -881 | G14: -673 | H14: -703 | I14: -729 | J14: -841 | K14: -1059 | L14: -1299 | M14: -1024
A15: Cash from Investing Activity - | B15: -432 | C15: -70 | D15: -126 | E15: -131 | F15: -52 | G15: 83 | H15: -321 | I15: -1920 | J15: -392 | K15: -927 | L15: -1237 | M15: -1811
A16: Fixed assets purchased | B16: -415 | C16: -151 | D16: -207 | E16: -199 | F16: -166 | G16: -155 | H16: -478 | I16: -735 | J16: -550 | K16: -1371 | L16: -1883 | M16: -2009
... A34: CFO/OP | B34: 1.1 | C34: 0.93 | D34: 1.06 | E34: 1.16 | F34: 1.12 | G34: 1.01 | H34: 0.99 | I34: 0.83 | J34: 0.97 | K34: 1 | L34: 0.94 | M34: 0.83

Sheet Data Sheet
A1: COMPANY NAME | B1: NESTLE INDIA LTD | E1: =IF(B2<>B3, "A NEW VERSION OF THE WORKSHEET IS AVAILABLE", "")
A2: LATEST VERSION | B2: 2.1 | E2: PLEASE DO NOT MAKE ANY CHANGES TO THIS SHEET
A3: CURRENT VERSION | B3: 2.1
A5: META
A6: Number of shares | B6: =IF(B9>0, B9/B8, 0) -> 192.83143
A7: Face Value | B7: 1
A8: Current Price | B8: 1259.35
A9: Market Capitalization | B9: 242842.26
A15: PROFIT & LOSS
A16: Report Date | B16: 42735 | C16: 43100 | D16: 43465 | E16: 43830 | F16: 44196 | G16: 44561 | H16: 44926 | I16: 45291 | J16: 45382 | K16: 45747
A17: Sales | B17: 9141.34 | C17: 10009.6 | D17: 11292.27 | E17: 12368.9 | F17: 13350.03 | G17: 14740.59 | H17: 16896.96 | I17: 19126.3 | J17: 24393.89 | K17: 20201.56
A18: Raw Material Cost | B18: 3227.26 | C18: 3696.99 | D18: 3829.22 | E18: 4520.91 | F18: 4901.74 | G18: 5301.26 | H18: 6660.42 | I18: 8472.72 | J18: 9201.11 | K18: 7646.63
A19: Change in Inventory | B19: 7.66 | C19: 79.56 | D19: 6.01 | E19: 144.19 | F19: 69.33 | G19: 67.59 | H19: 250.27 | I19: 40.01 | J19: 45.68 | K19: 139.66
A20: Power and Fuel | B20: 232.79 | C20: 288.44 | D20: 344.18 | E20: 340.53 | F20: 313.68 | G20: 408.06 | H20: 572.61 | J20: 674.83 | K20: 536.65
A21: Other Mfr. Exp | B21: 850.85 | C21: 897.84 | D21: 949.86 | E21: 1028.55 | F21: 1040.36 | G21: 1349.48 | H21: 1603.48 | J21: 1935.4 | K21: 1579.8
A22: Employee Cost | B22: 901.57 | C22: 1017.45 | D22: 1124.15 | E22: 1258.17 | F22: 1500.95 | G22: 1529.94 | H22: 1635.46 | I22: 1849.18 | J22: 2336.06 | K22: 2023.71
A23: Selling and admin | B23: 1751.78 | C23: 1823.98 | D23: 2145.82 | E23: 2226.13 | F23: 2246.9 | G23: 2902.12 | H23: 3192.15 | J23: 4837.58 | K23: 4121.66
A24: Other Expenses | B24: 334.91 | C24: 267.93 | D24: 287.4 | E24: 212.92 | F24: 214.23 | G24: -245.08 | H24: -223.18 | I24: 4373.42 | J24: -388.53 | K24: -338.56
A25: Other Income | B25: 140.12 | C25: 176.92 | D25: 258.92 | E25: 246.88 | F25: 145.85 | G25: -112.38 | H25: 107.26 | I25: 115.5 | J25: 158.99 | K25: 352.06
A26: Depreciation | B26: 353.67 | C26: 342.25 | D26: 335.67 | E26: 370.15 | F26: 370.38 | G26: 391.02 | H26: 403.01 | I26: 428.91 | J26: 567.75 | K26: 539.92
A27: Interest | B27: 90.91 | C27: 91.9 | D27: 111.95 | E27: 129.12 | F27: 164.18 | G27: 201.68 | H27: 154.57 | I27: 119.29 | J27: 145.49 | K27: 136
A28: Profit before tax | B28: 1545.38 | C28: 1839.3 | D28: 2428.95 | E28: 2673.49 | F28: 2812.79 | G28: 2857.32 | H28: 3255.97 | I28: 4038.29 | J28: 5288.87 | K28: 4447.47
A29: Tax | B29: 544.02 | C29: 614.11 | D29: 822.02 | E29: 705.05 | F29: 730.36 | G29: 738.91 | H29: 865.45 | I29: 1039.62 | J29: 1356.03 | K29: 1132.97
A30: Net profit | B30: 1001.36 | C30: 1225.19 | D30: 1606.93 | E30: 1968.44 | F30: 2082.43 | G30: 2118.41 | H30: 2390.52 | I30: 2998.67 | J30: 3932.84 | K30: 3314.5
A31: Dividend Amount | B31: 607.45 | C31: 829.21 | D31: 1108.83 | E31: 3297.56 | F31: 1928.4 | G31: 1928.4 | H31: 2121.24 | I31: 1677.71 | J31: 3104.72 | K31: 2603.34
A40: Quarters
A41: Report Date | B41: 45199 | C41: 45291 | D41: 45382 | E41: 45473 | F41: 45565 | G41: 45657 | H41: 45747 | I41: 45838 | J41: 45930 | K41: 46022
A42: Sales | B42: 5036.82 | C42: 4600.42 | D42: 5267.59 | E42: 4813.95 | F42: 5104 | G42: 4779.73 | H42: 5503.88 | I42: 5096.16 | J42: 5643.61 | K42: 5667.04
A43: Expenses | B43: 3811.95 | C43: 3505.3 | D43: 3917.54 | E43: 3699.62 | F43: 3936.27 | G43: 3677.04 | H43: 4114.92 | I43: 3995.9 | J43: 4406.97 | K43: 4464.97
A44: Other Income | B44: 139.69 | C44: -77 | D44: 36.83 | E44: 39.12 | F44: 297.68 | G44: 4.44 | H44: 8.44 | I44: 4.04 | J44: 1.64 | K44: 168.66
A45: Depreciation | B45: 111.16 | C45: 108.69 | D45: 110.1 | E45: 112.71 | F45: 121.6 | G45: 150.27 | H45: 155.34 | I45: 156.94 | J45: 163.35 | K45: 174.41
A46: Interest | B46: 31.38 | C46: 22.95 | D46: 26.2 | E46: 31.68 | F46: 32.22 | G46: 34.6 | H46: 37.5 | I46: 46.89 | J46: 46.41 | K46: 28.25
A47: Profit before tax | B47: 1222.02 | C47: 886.48 | D47: 1250.58 | E47: 1009.06 | F47: 1311.59 | G47: 922.26 | H47: 1204.56 | I47: 900.47 | J47: 1028.52 | K47: 1168.07
A48: Tax | B48: 313.94 | C48: 230.87 | D48: 316.41 | E48: 262.46 | F48: 325.23 | G48: 226.13 | H48: 319.15 | I48: 241.24 | J48: 275.32 | K48: 150.01
A49: Net profit | B49: 908.08 | C49: 655.61 | D49: 934.17 | E49: 746.6 | F49: 986.36 | G49: 696.13 | H49: 885.41 | I49: 659.23 | J49: 753.2 | K49: 1018.06
A50: Operating Profit | B50: 1224.87 | C50: 1095.12 | D50: 1350.05 | E50: 1114.33 | F50: 1167.73 | G50: 1102.69 | H50: 1388.96 | I50: 1100.26 | J50: 1236.64 | K50: 1202.07
A55: BALANCE SHEET
A56: Report Date | B56: 42735 | C56: 43100 | D56: 43465 | E56: 43830 | F56: 44196 | G56: 44561 | H56: 44926 | I56: 45291 | J56: 45382 | K56: 45747
A57: Equity Share Capital | B57: 96.42 | C57: 96.42 | D57: 96.42 | E57: 96.42 | F57: 96.42 | G57: 96.42 | H57: 96.42 | I57: 96.42 | J57: 96.42 | K57: 96.42
A58: Reserves | B58: 3185.91 | C58: 3324.17 | D58: 3577.32 | E58: 1822.45 | F58: 1922.92 | G58: 1849.96 | H58: 2362.75 | I58: 2362.75 | J58: 3244.47 | K58: 4020.73
A59: Borrowings | B59: 33.15 | C59: 35.14 | D59: 35.14 | E59: 188.94 | F59: 147.49 | G59: 266.46 | H59: 270.52 | I59: 270.52 | J59: 344.53 | K59: 1166.85
A60: Other Liabilities | B60: 3494.98 | C60: 3906.86 | D60: 4379.2 | E60: 5065.13 | F60: 5732.9 | G60: 6021.29 | H60: 6249.05 | I60: 6249.05 | J60: 6837.64 | K60: 7039.89
A61: Total | B61: 6810.46 | C61: 7362.59 | D61: 8088.08 | E61: 7172.94 | F61: 7899.73 | G61: 8234.13 | H61: 8978.74 | I61: 8978.74 | J61: 10523.06 | K61: 12323.89
A62: Net Block | B62: 2730.14 | C62: 2616.18 | D62: 2400.62 | E62: 2341.45 | F62: 2179.41 | G62: 2994.67 | H62: 3043.7 | I62: 3043.7 | J62: 3460.25 | K62: 5473.61
A63: Capital Work in Progress | B63: 188.17 | C63: 94.16 | D63: 105.2 | E63: 143.3 | F63: 638.58 | G63: 246.23 | H63: 358.36 | I63: 358.36 | J63: 1741.71 | K63: 1172.56
A64: Investments | B64: 1755.66 | C64: 1978.87 | D64: 2658.49 | E64: 1751.05 | F64: 1463.77 | G64: 773.98 | H64: 777.54 | I64: 777.54 | J64: 463.87 | K64: 705.6
A65: Other Assets | B65: 2136.49 | C65: 2673.38 | D65: 2923.77 | E65: 2937.14 | F65: 3617.97 | G65: 4219.25 | H65: 4799.14 | I65: 4799.14 | J65: 4857.23 | K65: 4972.12
A66: Total | B66: 6810.46 | C66: 7362.59 | D66: 8088.08 | E66: 7172.94 | F66: 7899.73 | G66: 8234.13 | H66: 8978.74 | I66: 8978.74 | J66: 10523.06 | K66: 12323.89
A67: Receivables | B67: 97.93 | C67: 88.97 | D67: 124.59 | E67: 124.33 | F67: 164.93 | G67: 165.97 | H67: 191.89 | I67: 191.89 | J67: 300.46 | K67: 363.15
... A69: Cash & Bank | B69: 880 | C69: 1457.42 | D69: 1610.06 | E69: 1308.05 | F69: 1769.87 | G69: 735.41 | H69: 945.55 | I69: 945.55 | J69: 778.85 | K69: 95.65
A70: No. of Equity Shares | B70: 96415716 | C70: 96415716 | D70: 96415716 | E70: 96415716 | F70: 96415716 | G70: 96415716 | H70: 96415716 | J70: 964157160 | K70: 964157160
A71: New Bonus Shares
A72: Face value | B72: 10 | C72: 10 | D72: 10 | E72: 10 | F72: 10 | G72: 10 | H72: 10 | I72: 10 | J72: 1 | K72: 1
A80: CASH FLOW:
A81: Report Date | B81: 42735 | C81: 43100 | D81: 43465 | E81: 43830 | F81: 44196 | G81: 44561 | H81: 44926 | I81: 45291 | J81: 45382 | K81: 45747
A82: Cash from Operating Activity | B82: 1465.91 | C82: 1817.79 | D82: 2052.45 | E82: 2295.25 | F82: 2454.48 | G82: 2236 | H82: 2737.43 | I82: 3392.19 | J82: 4174.79 | K82: 2936.35
A83: Cash from Investing Activity | B83: -125.9 | C83: -130.56 | D83: -52.41 | E83: 82.99 | F83: -321.46 | G83: -1920.33 | H83: -391.73 | I83: -926.99 | J83: -1237.42 | K83: -1810.9
A84: Cash from Financing Activity | B84: -665.61 | C84: -996.62 | D84: -1317.42 | E84: -3601.53 | F84: -1955.89 | G84: -2019.97 | H84: -2122.74 | I84: -2436.47 | J84: -3134.92 | K84: -1848.12
A85: Net Cash Flow | B85: 674.4 | C85: 690.61 | D85: 682.62 | E85: -1223.29 | F85: 177.13 | G85: -1704.3 | H85: 222.96 | I85: 28.73 | J85: -197.55 | K85: -722.67
A90: PRICE: | B90: 301.42 | C90: 393.55 | D90: 554.24 | E90: 739.27 | F90: 919.51 | G90: 985.29 | H90: 980.3 | I90: 1329.02 | J90: 1311.18 | K90: 1125.38
A92: DERIVED:
A93: Adjusted Equity Shares in Cr | B93: 192.8 | C93: 192.8 | D93: 192.8 | E93: 192.8 | F93: 192.8 | G93: 192.8 | H93: 192.8 | I93: 192.8 | J93: 192.83 | K93: 192.83

Sheet Historical FS
A1: Historical Financial Data - TATA MOTORS LTD
A2: Years | B2: 42705 | C2: =B2+365 -> 43070 | D2: =C2+365 -> 43435 | E2: =D2+365 -> 43800 | F2: =E2+366 -> 44166 | G2: =F2+366 -> 44532 | H2: =G2+366 -> 44898 | I2: =H2+366 -> 45264 | J2: 45352 | K2: =J2+366 -> 45718
A3: INCOME STATEMENT
A4: SALES | B4: =IFERROR('Data Sheet'!B17,0) -> 9141.34 | C4: =IFERROR('Data Sheet'!C17,0) -> 10009.6 | D4: =IFERROR('Data Sheet'!D17,0) -> 11292.27 | E4: =IFERROR('Data Sheet'!E17,0) -> 12368.9 | F4: =IFERROR('Data Sheet'!F17,0) -> 13350.03 | G4: =IFERROR('Data Sheet'!G17,0) -> 14740.59 | H4: =IFERROR('Data Sheet'!H17,0) -> 16896.96 | I4: =IFERROR('Data Sheet'!I17,0) -> 19126.3 | ... K4: =IFERROR('Data Sheet'!K17,0) -> 20201.56
A5: SALES GROWTH | C5: =C4/B4 -> 1.0949817 | D5: =D4/C4 -> 1.128144 | E5: =E4/D4 -> 1.0953422 | F5: =F4/E4 -> 1.0793223 | G5: =G4/F4 -> 1.1041616 | H5: =H4/G4 -> 1.1462879 | I5: =I4/H4 -> 1.1319373 | J5: =J4/I4 -> 1.2754108 | K5: =K4/J4 -> 0.82814016
A7: COGS | B7: =IFERROR(SUM('Data Sheet'!B18,'Data Sheet'!B20,'Data Sheet'!B21,'Data Sheet'!B22)-1*'Data Sheet'!B19,0) -> 5204.81 | C7: =IFERROR(SUM('Data Sheet'!C18,'Data Sheet'!C20,'Data Sheet'!C21,'Data Sheet'!C22)-1*'Data Sheet'!C19,0) -> 5821.16 | D7: =IFERROR(SUM('Data Sheet'!D18,'Data Sheet'!D20,'Data Sheet'!D21,'Data Sheet'!D22)-1*'Data Sheet'!D19,0) -> 6241.4 | E7: =IFERROR(SUM('Data Sheet'!E18,'Data Sheet'!E20,'Data Sheet'!E21,'Data Sheet'!E22)-1*'Data Sheet'!E19,0) -> 7003.97 | F7: =IFERROR(SUM('Data Sheet'!F18,'Data Sheet'!F20,'Data Sheet'!F21,'Data Sheet'!F22)-1*'Data Sheet'!F19,0) -> 7687.4 | G7: =IFERROR(SUM('Data Sheet'!G18,'Data Sheet'!G20,'Data Sheet'!G21,'Data Sheet'!G22)-1*'Data Sheet'!G19,0) -> 8521.15 | H7: =IFERROR(SUM('Data Sheet'!H18,'Data Sheet'!H20,'Data Sheet'!H21,'Data Sheet'!H22)-1*'Data Sheet'!H19,0) -> 10221.7 | I7: =IFERROR(SUM('Data Sheet'!I18,'Data Sheet'!I20,'Data Sheet'!I21,'Data Sheet'!I22)-1*'Data Sheet'!I19,0) -> 10281.89 | ... K7: =IFERROR(SUM('Data Sheet'!K18,'Data Sheet'!K20,'Data Sheet'!K21,'Data Sheet'!K22)-1*'Data Sheet'!K19,0) -> 11647.13
A8: COGS % SALES | B8: =B7/B4 -> 0.56937057 | C8: =C7/C4 -> 0.5815577 | D8: =D7/D4 -> 0.55271438 | E8: =E7/E4 -> 0.5662565 | F8: =F7/F4 -> 0.57583391 | G8: =G7/G4 -> 0.57807388 | H8: =H7/H4 -> 0.60494314 | I8: =I7/I4 -> 0.53757862 | ... K8: =K7/K4 -> 0.57654607
A10: GROSS PROFIT | B10: =B4-B7 -> 3936.53 | C10: =C4-C7 -> 4188.44 | D10: =D4-D7 -> 5050.87 | E10: =E4-E7 -> 5364.93 | F10: =F4-F7 -> 5662.63 | G10: =G4-G7 -> 6219.44 | H10: =H4-H7 -> 6675.26 | I10: =I4-I7 -> 8844.41 | ... K10: =K4-K7 -> 8554.43
A11: GROSS PROFIT MARGIN
A13: SELLING AND GEN. EXP | B13: =IFERROR(SUM('Data Sheet'!B23,'Data Sheet'!B24),0) -> 2086.69 | C13: =IFERROR(SUM('Data Sheet'!C23,'Data Sheet'!C24),0) -> 2091.91 | D13: =IFERROR(SUM('Data Sheet'!D23,'Data Sheet'!D24),0) -> 2433.22 | E13: =IFERROR(SUM('Data Sheet'!E23,'Data Sheet'!E24),0) -> 2439.05 | F13: =IFERROR(SUM('Data Sheet'!F23,'Data Sheet'!F24),0) -> 2461.13 | G13: =IFERROR(SUM('Data Sheet'!G23,'Data Sheet'!G24),0) -> 2657.04 | H13: =IFERROR(SUM('Data Sheet'!H23,'Data Sheet'!H24),0) -> 2968.97 | I13: =IFERROR(SUM('Data Sheet'!I23,'Data Sheet'!I24),0) -> 4373.42 | ... K13: =IFERROR(SUM('Data Sheet'!K23,'Data Sheet'!K24),0) -> 3783.1
A14: S & G % SALES | B14: =B13/B4 -> 0.2282696 | C14: =C13/C4 -> 0.20899037 | D14: =D13/D4 -> 0.2154766 | E14: =E13/E4 -> 0.19719215 | F14: =F13/F4 -> 0.18435389 | G14: =G13/G4 -> 0.1802533 | H14: =H13/H4 -> 0.17571031 | I14: =I13/I4 -> 0.22866001 | ... K14: =K13/K4 -> 0.18726772
A16: EBITDA | B16: =B10-B13 -> 1849.84 | C16: =C10-C13 -> 2096.53 | D16: =D10-D13 -> 2617.65 | E16: =E10-E13 -> 2925.88 | F16: =F10-F13 -> 3201.5 | G16: =G10-G13 -> 3562.4 | H16: =H10-H13 -> 3706.29 | I16: =I10-I13 -> 4470.99 | ... K16: =K10-K13 -> 4771.33
A17: EBITDA MARGIN | B17: =B16/B4 -> 0.20235983 | C17: =C16/C4 -> 0.20945193 | D17: =D16/D4 -> 0.23180902 | E17: =E16/E4 -> 0.23655135 | F17: =F16/F4 -> 0.2398122 | G17: =G16/G4 -> 0.24167282 | H17: =H16/H4 -> 0.21934656 | I17: =I16/I4 -> 0.23376137 | ... K17: =K16/K4 -> 0.23618622
A19: INTEREST | B19: =IFERROR('Data Sheet'!B27,0) -> 90.91 | C19: =IFERROR('Data Sheet'!C27,0) -> 91.9 | D19: =IFERROR('Data Sheet'!D27,0) -> 111.95 | E19: =IFERROR('Data Sheet'!E27,0) -> 129.12 | F19: =IFERROR('Data Sheet'!F27,0) -> 164.18 | G19: =IFERROR('Data Sheet'!G27,0) -> 201.68 | H19: =IFERROR('Data Sheet'!H27,0) -> 154.57 | I19: =IFERROR('Data Sheet'!I27,0) -> 119.29 | ... K19: =IFERROR('Data Sheet'!K27,0) -> 136
A20: INTEREST % SALES | B20: =B19/B4 -> 0.0099449315 | C20: =C19/C4 -> 0.0091811861 | D20: =D19/D4 -> 0.0099138614 | E20: =E19/E4 -> 0.010439085 | F20: =F19/F4 -> 0.0122981 | G20: =G19/G4 -> 0.013681949 | H20: =H19/H4 -> 0.0091477994 | I20: =I19/I4 -> 0.0062369617 | ... K20: =K19/K4 -> 0.0067321534
A22: DEPRICIATION | B22: =IFERROR('Data Sheet'!B26,0) -> 353.67 | C22: =IFERROR('Data Sheet'!C26,0) -> 342.25 | D22: =IFERROR('Data Sheet'!D26,0) -> 335.67 | E22: =IFERROR('Data Sheet'!E26,0) -> 370.15 | F22: =IFERROR('Data Sheet'!F26,0) -> 370.38 | G22: =IFERROR('Data Sheet'!G26,0) -> 391.02 | H22: =IFERROR('Data Sheet'!H26,0) -> 403.01 | I22: =IFERROR('Data Sheet'!I26,0) -> 428.91 | ... K22: =IFERROR('Data Sheet'!K26,0) -> 539.92
A23: DEP % SALES | B23: =B22/B4 -> 0.038689076 | C23: =C22/C4 -> 0.034192176 | D23: =D22/D4 -> 0.029725644 | E23: =E22/E4 -> 0.029925862 | F23: =F22/F4 -> 0.027743758 | G23: =G22/G4 -> 0.026526754 | H23: =H22/H4 -> 0.023851036 | I23: =I22/I4 -> 0.022425142 | ... K23: =K22/K4 -> 0.026726649
A25: EARNING BEFORE TAX | B25: =IFERROR('Data Sheet'!B28,0) -> 1545.38 | C25: =IFERROR('Data Sheet'!C28,0) -> 1839.3 | D25: =IFERROR('Data Sheet'!D28,0) -> 2428.95 | E25: =IFERROR('Data Sheet'!E28,0) -> 2673.49 | F25: =IFERROR('Data Sheet'!F28,0) -> 2812.79 | G25: =IFERROR('Data Sheet'!G28,0) -> 2857.32 | H25: =IFERROR('Data Sheet'!H28,0) -> 3255.97 | I25: =IFERROR('Data Sheet'!I28,0) -> 4038.29 | ... K25: =IFERROR('Data Sheet'!K28,0) -> 4447.47
A26: EBT % SALES | B26: =B25/B4 -> 0.16905399 | C26: =C25/C4 -> 0.1837536 | D26: =D25/D4 -> 0.21509847 | E26: =E25/E4 -> 0.21614614 | F26: =F25/F4 -> 0.21069541 | G26: =G25/G4 -> 0.19384027 | H26: =H25/H4 -> 0.19269561 | I26: =I25/I4 -> 0.21113807 | ... K26: =K25/K4 -> 0.22015478
A28: TAX | B28: =IFERROR('Data Sheet'!B29,0) -> 544.02 | C28: =IFERROR('Data Sheet'!C29,0) -> 614.11 | D28: =IFERROR('Data Sheet'!D29,0) -> 822.02 | E28: =IFERROR('Data Sheet'!E29,0) -> 705.05 | F28: =IFERROR('Data Sheet'!F29,0) -> 730.36 | G28: =IFERROR('Data Sheet'!G29,0) -> 738.91 | H28: =IFERROR('Data Sheet'!H29,0) -> 865.45 | I28: =IFERROR('Data Sheet'!I29,0) -> 1039.62 | ... K28: =IFERROR('Data Sheet'!K29,0) -> 1132.97
A29: EFFECTIVE TAX RATE | B29: =B28/B4 -> 0.059512063 | C29: =C28/C4 -> 0.061352102 | D29: =D28/D4 -> 0.07279493 | E29: =E28/E4 -> 0.057001835 | F29: =F28/F4 -> 0.054708491 | G29: =G28/G4 -> 0.050127573 | H29: =H28/H4 -> 0.051219273 | I29: =I28/I4 -> 0.054355521 | ... K29: =K28/K4 -> 0.056083293
A31: NET PROFIT | B31: =B25-B28 -> 1001.36 | C31: =C25-C28 -> 1225.19 | D31: =D25-D28 -> 1606.93 | E31: =E25-E28 -> 1968.44 | F31: =F25-F28 -> 2082.43 | G31: =G25-G28 -> 2118.41 | H31: =H25-H28 -> 2390.52 | I31: =I25-I28 -> 2998.67 | ... K31: =K25-K28 -> 3314.5
A32: NET MARGIN | B32: =B31/B4 -> 0.10954193 | C32: =C31/C4 -> 0.12240149 | D32: =D31/D4 -> 0.14230354 | E32: =E31/E4 -> 0.15914431 | F32: =F31/F4 -> 0.15598692 | G32: =G31/G4 -> 0.1437127 | H32: =H31/H4 -> 0.14147634 | I32: =I31/I4 -> 0.15678255 | ... K32: =K31/K4 -> 0.16407149
A34: No. of Equity Shareholders Outstanding | B34: =IFERROR('Data Sheet'!B93,0) -> 192.8 | C34: =IFERROR('Data Sheet'!C93,0) -> 192.8 | D34: =IFERROR('Data Sheet'!D93,0) -> 192.8 | E34: =IFERROR('Data Sheet'!E93,0) -> 192.8 | F34: =IFERROR('Data Sheet'!F93,0) -> 192.8 | G34: =IFERROR('Data Sheet'!G93,0) -> 192.8 | H34: =IFERROR('Data Sheet'!H93,0) -> 192.8 | I34: =IFERROR('Data Sheet'!I93,0) -> 192.8 | ... K34: =IFERROR('Data Sheet'!K93,0) -> 192.83
A36: EPS | B36: =B31/B34 -> 5.1937759 | C36: =C31/C34 -> 6.3547199 | D36: =D31/D34 -> 8.3346992 | E36: =E31/E34 -> 10.209751 | F36: =F31/F34 -> 10.800985 | G36: =G31/G34 -> 10.987604 | H36: =H31/H34 -> 12.398963 | I36: =I31/I34 -> 15.553268 | ... K36: =K31/K34 -> 17.188715
A37: EPS GROWTH
A38: DPS | B38: =IFERROR('Data Sheet'!B31/'Historical FS'!B34,0) -> 3.1506743 | C38: =IFERROR('Data Sheet'!C31/'Historical FS'!C34,0) -> 4.3008817 | D38: =IFERROR('Data Sheet'!D31/'Historical FS'!D34,0) -> 5.7511929 | E38: =IFERROR('Data Sheet'!E31/'Historical FS'!E34,0) -> 17.103527 | F38: =IFERROR('Data Sheet'!F31/'Historical FS'!F34,0) -> 10.002075 | G38: =IFERROR('Data Sheet'!G31/'Historical FS'!G34,0) -> 10.002075 | H38: =IFERROR('Data Sheet'!H31/'Historical FS'!H34,0) -> 11.002282 | I38: =IFERROR('Data Sheet'!I31/'Historical FS'!I34,0) -> 8.7018154 | ... K38: =IFERROR('Data Sheet'!K31/'Historical FS'!K34,0) -> 13.5007
A39: DPS RATIO | B39: =IFERROR(B38/B36,0) -> 0.60662499 | C39: =IFERROR(C38/C36,0) -> 0.67680115 | D39: =IFERROR(D38/D36,0) -> 0.69003006 | E39: =IFERROR(E38/E36,0) -> 1.6752149 | F39: =IFERROR(F38/F36,0) -> 0.92603353 | G39: =IFERROR(G38/G36,0) -> 0.91030537 | H39: =IFERROR(H38/H36,0) -> 0.88735505 | I39: =IFERROR(I38/I36,0) -> 0.5594847 | ... K39: =IFERROR(K38/K36,0) -> 0.78543973
A41: RETAINED EARNING | B41: =IFERROR(1-B39,0) -> 0.39337501 | C41: =IFERROR(1-C39,0) -> 0.32319885 | D41: =IFERROR(1-D39,0) -> 0.30996994 | E41: =IFERROR(1-E39,0) -> -0.67521489 | F41: =IFERROR(1-F39,0) -> 0.073966472 | G41: =IFERROR(1-G39,0) -> 0.089694629 | H41: =IFERROR(1-H39,0) -> 0.11264495 | I41: =IFERROR(1-I39,0) -> 0.4405153 | ... K41: =IFERROR(1-K39,0) -> 0.21456027
B42: =IFERROR(IF(B36>B38,1-B39,0),0) -> 0.39337501 | C42: =IFERROR(IF(C36>C38,1-C39,0),0) -> 0.32319885 | D42: =IFERROR(IF(D36>D38,1-D39,0),0) -> 0.30996994 | E42: =IFERROR(IF(E36>E38,1-E39,0),0) -> 0 | F42: =IFERROR(IF(F36>F38,1-F39,0),0) -> 0.073966472 | G42: =IFERROR(IF(G36>G38,1-G39,0),0) -> 0.089694629 | H42: =IFERROR(IF(H36>H38,1-H39,0),0) -> 0.11264495 | I42: =IFERROR(IF(I36>I38,1-I39,0),0) -> 0.4405153 | ... K42: =IFERROR(IF(K36>K38,1-K39,0),0) -> 0.21456027
A44: BALANCE SHEET
A45: Equity Share Capital | B45: =IFERROR('Data Sheet'!B57,0) -> 96.42 | C45: =IFERROR('Data Sheet'!C57,0) -> 96.42 | D45: =IFERROR('Data Sheet'!D57,0) -> 96.42 | E45: =IFERROR('Data Sheet'!E57,0) -> 96.42 | F45: =IFERROR('Data Sheet'!F57,0) -> 96.42 | G45: =IFERROR('Data Sheet'!G57,0) -> 96.42 | H45: =IFERROR('Data Sheet'!H57,0) -> 96.42 | I45: =IFERROR('Data Sheet'!I57,0) -> 96.42 | ... K45: =IFERROR('Data Sheet'!K57,0) -> 96.42
A46: Reserves | B46: =IFERROR('Data Sheet'!B58,0) -> 3185.91 | C46: =IFERROR('Data Sheet'!C58,0) -> 3324.17 | D46: =IFERROR('Data Sheet'!D58,0) -> 3577.32 | E46: =IFERROR('Data Sheet'!E58,0) -> 1822.45 | F46: =IFERROR('Data Sheet'!F58,0) -> 1922.92 | G46: =IFERROR('Data Sheet'!G58,0) -> 1849.96 | H46: =IFERROR('Data Sheet'!H58,0) -> 2362.75 | I46: =IFERROR('Data Sheet'!I58,0) -> 2362.75 | ... K46: =IFERROR('Data Sheet'!K58,0) -> 4020.73
A47: Borrowings | B47: =IFERROR('Data Sheet'!B59,0) -> 33.15 | C47: =IFERROR('Data Sheet'!C59,0) -> 35.14 | D47: =IFERROR('Data Sheet'!D59,0) -> 35.14 | E47: =IFERROR('Data Sheet'!E59,0) -> 188.94 | F47: =IFERROR('Data Sheet'!F59,0) -> 147.49 | G47: =IFERROR('Data Sheet'!G59,0) -> 266.46 | H47: =IFERROR('Data Sheet'!H59,0) -> 270.52 | I47: =IFERROR('Data Sheet'!I59,0) -> 270.52 | ... K47: =IFERROR('Data Sheet'!K59,0) -> 1166.85
A48: Other Liabilities | B48: =IFERROR('Data Sheet'!B60,0) -> 3494.98 | C48: =IFERROR('Data Sheet'!C60,0) -> 3906.86 | D48: =IFERROR('Data Sheet'!D60,0) -> 4379.2 | E48: =IFERROR('Data Sheet'!E60,0) -> 5065.13 | F48: =IFERROR('Data Sheet'!F60,0) -> 5732.9 | G48: =IFERROR('Data Sheet'!G60,0) -> 6021.29 | H48: =IFERROR('Data Sheet'!H60,0) -> 6249.05 | I48: =IFERROR('Data Sheet'!I60,0) -> 6249.05 | ... K48: =IFERROR('Data Sheet'!K60,0) -> 7039.89
A49: Total Liabilities | B49: =SUM(B45:B48) -> 6810.46 | C49: =SUM(C45:C48) -> 7362.59 | D49: =SUM(D45:D48) -> 8088.08 | E49: =SUM(E45:E48) -> 7172.94 | F49: =SUM(F45:F48) -> 7899.73 | G49: =SUM(G45:G48) -> 8234.13 | H49: =SUM(H45:H48) -> 8978.74 | I49: =SUM(I45:I48) -> 8978.74 | ... K49: =SUM(K45:K48) -> 12323.89
A51: Fixed Asset Net Block | B51: =IFERROR('Data Sheet'!B62,0) -> 2730.14 | C51: =IFERROR('Data Sheet'!C62,0) -> 2616.18 | D51: =IFERROR('Data Sheet'!D62,0) -> 2400.62 | E51: =IFERROR('Data Sheet'!E62,0) -> 2341.45 | F51: =IFERROR('Data Sheet'!F62,0) -> 2179.41 | G51: =IFERROR('Data Sheet'!G62,0) -> 2994.67 | H51: =IFERROR('Data Sheet'!H62,0) -> 3043.7 | I51: =IFERROR('Data Sheet'!I62,0) -> 3043.7 | ... K51: =IFERROR('Data Sheet'!K62,0) -> 5473.61
A52: Capital Work in Progress | B52: =IFERROR('Data Sheet'!B63,0) -> 188.17 | C52: =IFERROR('Data Sheet'!C63,0) -> 94.16 | D52: =IFERROR('Data Sheet'!D63,0) -> 105.2 | E52: =IFERROR('Data Sheet'!E63,0) -> 143.3 | F52: =IFERROR('Data Sheet'!F63,0) -> 638.58 | G52: =IFERROR('Data Sheet'!G63,0) -> 246.23 | H52: =IFERROR('Data Sheet'!H63,0) -> 358.36 | I52: =IFERROR('Data Sheet'!I63,0) -> 358.36 | ... K52: =IFERROR('Data Sheet'!K63,0) -> 1172.56
A53: Investments | B53: =IFERROR('Data Sheet'!B64,0) -> 1755.66 | C53: =IFERROR('Data Sheet'!C64,0) -> 1978.87 | D53: =IFERROR('Data Sheet'!D64,0) -> 2658.49 | E53: =IFERROR('Data Sheet'!E64,0) -> 1751.05 | F53: =IFERROR('Data Sheet'!F64,0) -> 1463.77 | G53: =IFERROR('Data Sheet'!G64,0) -> 773.98 | H53: =IFERROR('Data Sheet'!H64,0) -> 777.54 | I53: =IFERROR('Data Sheet'!I64,0) -> 777.54 | ... K53: =IFERROR('Data Sheet'!K64,0) -> 705.6
A54: Other Assets | B54: ='Data Sheet'!B65-SUM('Data Sheet'!B67:B69) -> 218.5 | C54: ='Data Sheet'!C65-SUM('Data Sheet'!C67:C69) -> 224.52 | D54: ='Data Sheet'!D65-SUM('Data Sheet'!D67:D69) -> 223.57 | E54: ='Data Sheet'!E65-SUM('Data Sheet'!E67:E69) -> 221.69 | F54: ='Data Sheet'!F65-SUM('Data Sheet'!F67:F69) -> 266.69 | G54: ='Data Sheet'!G65-SUM('Data Sheet'!G67:G69) -> 1725.22 | H54: ='Data Sheet'!H65-SUM('Data Sheet'!H67:H69) -> 1732.93 | I54: ='Data Sheet'!I65-SUM('Data Sheet'!I67:I69) -> 1732.93 | ... K54: ='Data Sheet'!K65-SUM('Data Sheet'!K67:K69) -> 1663.18
A55: Total Non Current Assets | B55: =SUM(B51:B54) -> 4892.47 | C55: =SUM(C51:C54) -> 4913.73 | D55: =SUM(D51:D54) -> 5387.88 | E55: =SUM(E51:E54) -> 4457.49 | F55: =SUM(F51:F54) -> 4548.45 | G55: =SUM(G51:G54) -> 5740.1 | H55: =SUM(H51:H54) -> 5912.53 | I55: =SUM(I51:I54) -> 5912.53 | ... K55: =SUM(K51:K54) -> 9014.95
A57: Receivables | B57: =IFERROR('Data Sheet'!B67,0) -> 97.93 | C57: =IFERROR('Data Sheet'!C67,0) -> 88.97 | D57: =IFERROR('Data Sheet'!D67,0) -> 124.59 | E57: =IFERROR('Data Sheet'!E67,0) -> 124.33 | F57: =IFERROR('Data Sheet'!F67,0) -> 164.93 | G57: =IFERROR('Data Sheet'!G67,0) -> 165.97 | H57: =IFERROR('Data Sheet'!H67,0) -> 191.89 | I57: =IFERROR('Data Sheet'!I67,0) -> 191.89 | ... K57: =IFERROR('Data Sheet'!K67,0) -> 363.15
A58: Inventory | B58: =IFERROR('Data Sheet'!B68,0) -> 940.06 | C58: =IFERROR('Data Sheet'!C68,0) -> 902.47 | D58: =IFERROR('Data Sheet'!D68,0) -> 965.55 | E58: =IFERROR('Data Sheet'!E68,0) -> 1283.07 | F58: =IFERROR('Data Sheet'!F68,0) -> 1416.48 | G58: =IFERROR('Data Sheet'!G68,0) -> 1592.65 | H58: =IFERROR('Data Sheet'!H68,0) -> 1928.77 | I58: =IFERROR('Data Sheet'!I68,0) -> 1928.77 | ... K58: =IFERROR('Data Sheet'!K68,0) -> 2850.14
A59: Cash & Bank | B59: =IFERROR('Data Sheet'!B69,0) -> 880 | C59: =IFERROR('Data Sheet'!C69,0) -> 1457.42 | D59: =IFERROR('Data Sheet'!D69,0) -> 1610.06 | E59: =IFERROR('Data Sheet'!E69,0) -> 1308.05 | F59: =IFERROR('Data Sheet'!F69,0) -> 1769.87 | G59: =IFERROR('Data Sheet'!G69,0) -> 735.41 | H59: =IFERROR('Data Sheet'!H69,0) -> 945.55 | I59: =IFERROR('Data Sheet'!I69,0) -> 945.55 | ... K59: =IFERROR('Data Sheet'!K69,0) -> 95.65
A60: Total Current Assets | B60: =SUM(B57:B59) -> 1917.99 | C60: =SUM(C57:C59) -> 2448.86 | D60: =SUM(D57:D59) -> 2700.2 | E60: =SUM(E57:E59) -> 2715.45 | F60: =SUM(F57:F59) -> 3351.28 | G60: =SUM(G57:G59) -> 2494.03 | H60: =SUM(H57:H59) -> 3066.21 | I60: =SUM(I57:I59) -> 3066.21 | ... K60: =SUM(K57:K59) -> 3308.94
A62: Total Assets | B62: =SUM(B55,B60) -> 6810.46 | C62: =SUM(C55,C60) -> 7362.59 | D62: =SUM(D55,D60) -> 8088.08 | E62: =SUM(E55,E60) -> 7172.94 | F62: =SUM(F55,F60) -> 7899.73 | G62: =SUM(G55,G60) -> 8234.13 | H62: =SUM(H55,H60) -> 8978.74 | I62: =SUM(I55,I60) -> 8978.74 | ... K62: =SUM(K55,K60) -> 12323.89
A64: CHECK | B64: =B49=B62 -> TRUE | C64: =C49=C62 -> TRUE | D64: =D49=D62 -> TRUE | E64: =E49=E62 -> TRUE | F64: =F49=F62 -> TRUE | G64: =G49=G62 -> TRUE | H64: =H49=H62 -> TRUE | I64: =I49=I62 -> TRUE | ... K64: =K49=K62 -> TRUE
A67: CASH FLOW STATEMENT
A68: Operating Activities
A69: Profit from operations | B69: =IFERROR('cash flows'!D6,0) -> 1765 | C69: =IFERROR('cash flows'!E6,0) -> 2047 | D69: =IFERROR('cash flows'!F6,0) -> 2521 | E69: =IFERROR('cash flows'!G6,0) -> 2805 | F69: =IFERROR('cash flows'!H6,0) -> 3061 | G69: =IFERROR('cash flows'!I6,0) -> 3136 | H69: =IFERROR('cash flows'!J6,0) -> 3609 | I69: =IFERROR('cash flows'!K6,0) -> 4388 | ... K69: =IFERROR('cash flows'!M6,0) -> 4672
A70: Receivables | B70: =IFERROR('cash flows'!D7,0) -> -19 | C70: =IFERROR('cash flows'!E7,0) -> 8 | D70: =IFERROR('cash flows'!F7,0) -> -36 | E70: =IFERROR('cash flows'!G7,0) -> 0 | F70: =IFERROR('cash flows'!H7,0) -> -42 | G70: =IFERROR('cash flows'!I7,0) -> -2 | H70: =IFERROR('cash flows'!J7,0) -> -28 | I70: =IFERROR('cash flows'!K7,0) -> -11 | ... K70: =IFERROR('cash flows'!M7,0) -> -70
A71: Inventory | B71: =IFERROR('cash flows'!D8,0) -> -119 | C71: =IFERROR('cash flows'!E8,0) -> 38 | D71: =IFERROR('cash flows'!F8,0) -> -63 | E71: =IFERROR('cash flows'!G8,0) -> -318 | F71: =IFERROR('cash flows'!H8,0) -> -133 | G71: =IFERROR('cash flows'!I8,0) -> -169 | H71: =IFERROR('cash flows'!J8,0) -> -336 | I71: =IFERROR('cash flows'!K8,0) -> 56 | ... K71: =IFERROR('cash flows'!M8,0) -> -767
A72: Payables | B72: =IFERROR('cash flows'!D9,0) -> 50 | C72: =IFERROR('cash flows'!E9,0) -> 185 | D72: =IFERROR('cash flows'!F9,0) -> 257 | E72: =IFERROR('cash flows'!G9,0) -> 253 | F72: =IFERROR('cash flows'!H9,0) -> 23 | G72: =IFERROR('cash flows'!I9,0) -> 217 | H72: =IFERROR('cash flows'!J9,0) -> 178 | I72: =IFERROR('cash flows'!K9,0) -> 68 | ... K72: =IFERROR('cash flows'!M9,0) -> 134
A73: Loans Advances | B73: =IFERROR('cash flows'!D10,0) -> 0 | C73: =IFERROR('cash flows'!E10,0) -> 0 | D73: =IFERROR('cash flows'!F10,0) -> 0 | E73: =IFERROR('cash flows'!G10,0) -> 0 | F73: =IFERROR('cash flows'!H10,0) -> 0 | G73: =IFERROR('cash flows'!I10,0) -> -40 | H73: =IFERROR('cash flows'!J10,0) -> -30 | I73: =IFERROR('cash flows'!K10,0) -> -30 | ... K73: =IFERROR('cash flows'!M10,0) -> -199
A74: Other WC items | B74: =IFERROR('cash flows'!D12,0) -> 293 | C74: =IFERROR('cash flows'!E12,0) -> 144 | D74: =IFERROR('cash flows'!F12,0) -> 255 | E74: =IFERROR('cash flows'!G12,0) -> 227 | F74: =IFERROR('cash flows'!H12,0) -> 249 | G74: =IFERROR('cash flows'!I12,0) -> -179 | H74: =IFERROR('cash flows'!J12,0) -> 185 | I74: =IFERROR('cash flows'!K12,0) -> -19 | ... K74: =IFERROR('cash flows'!M12,0) -> 191
A75: Working capital changes | B75: =IFERROR('cash flows'!D13,0) -> 204 | C75: =IFERROR('cash flows'!E13,0) -> 375 | D75: =IFERROR('cash flows'!F13,0) -> 413 | E75: =IFERROR('cash flows'!G13,0) -> 163 | F75: =IFERROR('cash flows'!H13,0) -> 97 | G75: =IFERROR('cash flows'!I13,0) -> -172 | H75: =IFERROR('cash flows'!J13,0) -> -30 | I75: =IFERROR('cash flows'!K13,0) -> 63 | ... K75: =IFERROR('cash flows'!M13,0) -> -711
A76: Direct taxes | B76: =IFERROR('cash flows'!D14,0) -> -503 | C76: =IFERROR('cash flows'!E14,0) -> -604 | D76: =IFERROR('cash flows'!F14,0) -> -881 | E76: =IFERROR('cash flows'!G14,0) -> -673 | F76: =IFERROR('cash flows'!H14,0) -> -703 | G76: =IFERROR('cash flows'!I14,0) -> -729 | H76: =IFERROR('cash flows'!J14,0) -> -841 | I76: =IFERROR('cash flows'!K14,0) -> -1059 | ... K76: =IFERROR('cash flows'!M14,0) -> -1024
A77: Cash From Operating Activities | B77: =SUM(B69:B74)+B76 -> 1467 | C77: =SUM(C69:C74)+C76 -> 1818 | D77: =SUM(D69:D74)+D76 -> 2053 | E77: =SUM(E69:E74)+E76 -> 2294 | F77: =SUM(F69:F74)+F76 -> 2455 | G77: =SUM(G69:G74)+G76 -> 2234 | H77: =SUM(H69:H74)+H76 -> 2737 | I77: =SUM(I69:I74)+I76 -> 3393 | ... K77: =SUM(K69:K74)+K76 -> 2937
A80: Investing Activities
A81: Fixed assets purchased | B81: =IFERROR('cash flows'!D16,0) -> -207 | C81: =IFERROR('cash flows'!E16,0) -> -199 | D81: =IFERROR('cash flows'!F16,0) -> -166 | E81: =IFERROR('cash flows'!G16,0) -> -155 | F81: =IFERROR('cash flows'!H16,0) -> -478 | G81: =IFERROR('cash flows'!I16,0) -> -735 | H81: =IFERROR('cash flows'!J16,0) -> -550 | I81: =IFERROR('cash flows'!K16,0) -> -1371 | ... K81: =IFERROR('cash flows'!M16,0) -> -2009
A82: Fixed assets sold | B82: =IFERROR('cash flows'!D17,0) -> 94 | C82: =IFERROR('cash flows'!E17,0) -> 3 | D82: =IFERROR('cash flows'!F17,0) -> 3 | E82: =IFERROR('cash flows'!G17,0) -> 2 | F82: =IFERROR('cash flows'!H17,0) -> 4 | G82: =IFERROR('cash flows'!I17,0) -> 4 | H82: =IFERROR('cash flows'!J17,0) -> 9 | I82: =IFERROR('cash flows'!K17,0) -> 7 | ... K82: =IFERROR('cash flows'!M17,0) -> 4
A83: Investments purchased | B83: =IFERROR('cash flows'!D18,0) -> -153 | C83: =IFERROR('cash flows'!E18,0) -> -112 | D83: =IFERROR('cash flows'!F18,0) -> -160 | E83: =IFERROR('cash flows'!G18,0) -> -16 | F83: =IFERROR('cash flows'!H18,0) -> 0 | G83: =IFERROR('cash flows'!I18,0) -> 0 | H83: =IFERROR('cash flows'!J18,0) -> 0 | I83: =IFERROR('cash flows'!K18,0) -> 0 | ... K83: =IFERROR('cash flows'!M18,0) -> 0
A84: Investments sold | B84: =IFERROR('cash flows'!D19,0) -> 0 | C84: =IFERROR('cash flows'!E19,0) -> 0 | D84: =IFERROR('cash flows'!F19,0) -> 0 | E84: =IFERROR('cash flows'!G19,0) -> 0 | F84: =IFERROR('cash flows'!H19,0) -> 0 | G84: =IFERROR('cash flows'!I19,0) -> 0 | H84: =IFERROR('cash flows'!J19,0) -> 25 | I84: =IFERROR('cash flows'!K19,0) -> 312 | ... K84: =IFERROR('cash flows'!M19,0) -> 424
A85: Interest received | B85: =IFERROR('cash flows'!D20,0) -> 126 | C85: =IFERROR('cash flows'!E20,0) -> 154 | D85: =IFERROR('cash flows'!F20,0) -> 237 | E85: =IFERROR('cash flows'!G20,0) -> 238 | F85: =IFERROR('cash flows'!H20,0) -> 148 | G85: =IFERROR('cash flows'!I20,0) -> 125 | H85: =IFERROR('cash flows'!J20,0) -> 103 | I85: =IFERROR('cash flows'!K20,0) -> 0 | ... K85: =IFERROR('cash flows'!M20,0) -> 76
A86: Dividends received | B86: =IFERROR('cash flows'!D21,0) -> 13 | C86: =IFERROR('cash flows'!E21,0) -> 16 | D86: =IFERROR('cash flows'!F21,0) -> 19 | E86: =IFERROR('cash flows'!G21,0) -> 13 | F86: =IFERROR('cash flows'!H21,0) -> 2 | G86: =IFERROR('cash flows'!I21,0) -> 0 | H86: =IFERROR('cash flows'!J21,0) -> 0 | I86: =IFERROR('cash flows'!K21,0) -> 0 | ... K86: =IFERROR('cash flows'!M21,0) -> 0
A87: Acquisition of companies | B87: =IFERROR('cash flows'!D22,0) -> 0 | C87: =IFERROR('cash flows'!E22,0) -> 0 | D87: =IFERROR('cash flows'!F22,0) -> 0 | E87: =IFERROR('cash flows'!G22,0) -> 0 | F87: =IFERROR('cash flows'!H22,0) -> 0 | G87: =IFERROR('cash flows'!I22,0) -> 0 | H87: =IFERROR('cash flows'!J22,0) -> 0 | I87: =IFERROR('cash flows'!K22,0) -> 0 | ... K87: =IFERROR('cash flows'!M22,0) -> -706
A88: Other investing items | B88: =IFERROR('cash flows'!D23,0) -> 1 | C88: =IFERROR('cash flows'!E23,0) -> 7 | D88: =IFERROR('cash flows'!F23,0) -> 15 | E88: =IFERROR('cash flows'!G23,0) -> 0 | F88: =IFERROR('cash flows'!H23,0) -> 3 | G88: =IFERROR('cash flows'!I23,0) -> -1314 | H88: =IFERROR('cash flows'!J23,0) -> 20 | I88: =IFERROR('cash flows'!K23,0) -> 126 | ... K88: =IFERROR('cash flows'!M23,0) -> 400
A89: Cash From Investing Activities | B89: =SUM(B81:B88) -> -126 | C89: =SUM(C81:C88) -> -131 | D89: =SUM(D81:D88) -> -52 | E89: =SUM(E81:E88) -> 82 | F89: =SUM(F81:F88) -> -321 | G89: =SUM(G81:G88) -> -1920 | H89: =SUM(H81:H88) -> -393 | I89: =SUM(I81:I88) -> -926 | ... K89: =SUM(K81:K88) -> -1811
A91: Financing Activities
A92: Proceeds from shares | B92: =IFERROR('cash flows'!D25,0) -> 0 | C92: =IFERROR('cash flows'!E25,0) -> 0 | D92: =IFERROR('cash flows'!F25,0) -> 0 | E92: =IFERROR('cash flows'!G25,0) -> 0 | F92: =IFERROR('cash flows'!H25,0) -> 0 | G92: =IFERROR('cash flows'!I25,0) -> 24 | H92: =IFERROR('cash flows'!J25,0) -> 0 | I92: =IFERROR('cash flows'!K25,0) -> 0 | ... K92: =IFERROR('cash flows'!M25,0) -> 726
A93: Investment subsidy | B93: =IFERROR('cash flows'!D27,0) -> 0 | C93: =IFERROR('cash flows'!E27,0) -> 0 | D93: =IFERROR('cash flows'!F27,0) -> 0 | E93: =IFERROR('cash flows'!G27,0) -> 0 | F93: =IFERROR('cash flows'!H27,0) -> 0 | G93: =IFERROR('cash flows'!I27,0) -> 0 | H93: =IFERROR('cash flows'!J27,0) -> 0 | I93: =IFERROR('cash flows'!K27,0) -> 0 | ... K93: =IFERROR('cash flows'!M27,0) -> 0
A94: Repayment of borrowings | B94: =IFERROR('cash flows'!D26,0) -> 0 | C94: =IFERROR('cash flows'!E26,0) -> 0 | D94: =IFERROR('cash flows'!F26,0) -> 0 | E94: =IFERROR('cash flows'!G26,0) -> 0 | F94: =IFERROR('cash flows'!H26,0) -> 0 | G94: =IFERROR('cash flows'!I26,0) -> -24 | H94: =IFERROR('cash flows'!J26,0) -> 0 | I94: =IFERROR('cash flows'!K26,0) -> 0 | ... K94: =IFERROR('cash flows'!M26,0) -> 0
A95: Interest paid fin | B95: =IFERROR('cash flows'!D28,0) -> -4 | C95: =IFERROR('cash flows'!E28,0) -> -1 | D95: =IFERROR('cash flows'!F28,0) -> -4 | E95: =IFERROR('cash flows'!G28,0) -> -63 | F95: =IFERROR('cash flows'!H28,0) -> -69 | G95: =IFERROR('cash flows'!I28,0) -> -9 | H95: =IFERROR('cash flows'!J28,0) -> -18 | I95: =IFERROR('cash flows'!K28,0) -> -20 | ... K95: =IFERROR('cash flows'!M28,0) -> -34
A96: Dividends paid | B96: =IFERROR('cash flows'!D29,0) -> -564 | C96: =IFERROR('cash flows'!E29,0) -> -829 | D96: =IFERROR('cash flows'!F29,0) -> -1090 | E96: =IFERROR('cash flows'!G29,0) -> -2950 | F96: =IFERROR('cash flows'!H29,0) -> -1890 | G96: =IFERROR('cash flows'!I29,0) -> -1928 | H96: =IFERROR('cash flows'!J29,0) -> -2025 | I96: =IFERROR('cash flows'!K29,0) -> -2333 | ... K96: =IFERROR('cash flows'!M29,0) -> -2459
A97: Financial liabilities | B97: =IFERROR('cash flows'!D30,0) -> 0 | C97: =IFERROR('cash flows'!E30,0) -> 0 | D97: =IFERROR('cash flows'!F30,0) -> 0 | E97: =IFERROR('cash flows'!G30,0) -> 0 | F97: =IFERROR('cash flows'!H30,0) -> 0 | G97: =IFERROR('cash flows'!I30,0) -> -79 | H97: =IFERROR('cash flows'!J30,0) -> -73 | I97: =IFERROR('cash flows'!K30,0) -> -166 | ... K97: =IFERROR('cash flows'!M30,0) -> -76
A98: Other financing items | B98: =IFERROR('cash flows'!D31,0) -> -98 | C98: =IFERROR('cash flows'!E31,0) -> -167 | D98: =IFERROR('cash flows'!F31,0) -> -224 | E98: =IFERROR('cash flows'!G31,0) -> -588 | F98: =IFERROR('cash flows'!H31,0) -> 3 | G98: =IFERROR('cash flows'!I31,0) -> -3 | H98: =IFERROR('cash flows'!J31,0) -> -7 | I98: =IFERROR('cash flows'!K31,0) -> 83 | ... K98: =IFERROR('cash flows'!M31,0) -> -5
A99: Cash From Financing Activities | B99: =SUM(B92:B98) -> -666 | C99: =SUM(C92:C98) -> -997 | D99: =SUM(D92:D98) -> -1318 | E99: =SUM(E92:E98) -> -3601 | F99: =SUM(F92:F98) -> -1956 | G99: =SUM(G92:G98) -> -2019 | H99: =SUM(H92:H98) -> -2123 | I99: =SUM(I92:I98) -> -2436 | ... K99: =SUM(K92:K98) -> -1848
A101: Net Cash Flow | B101: =SUM(B77,B89,B99) -> 675 | C101: =SUM(C77,C89,C99) -> 690 | D101: =SUM(D77,D89,D99) -> 683 | E101: =SUM(E77,E89,E99) -> -1225 | F101: =SUM(F77,F89,F99) -> 178 | G101: =SUM(G77,G89,G99) -> -1705 | H101: =SUM(H77,H89,H99) -> 221 | I101: =SUM(I77,I89,I99) -> 31 | ... K101: =SUM(K77,K89,K99) -> -722

Sheet Ratio Analysis
A1: Ratio Analysis-TATA MOTORS LTD
A2: Years | B2: 42705 | C2: =B2+365 -> 43070 | D2: =C2+365 -> 43435 | E2: =D2+365 -> 43800 | F2: =E2+366 -> 44166 | G2: =F2+366 -> 44532 | H2: =G2+366 -> 44898 | I2: =H2+366 -> 45264 | J2: 45352 | K2: =J2+366 -> 45718 | M2: Mean | N2: Median
A3: Sales Growth | B3: =IFERROR('Historical FS'!B4,0) -> 9141.34 | C3: =IFERROR('Historical FS'!C4,0) -> 10009.6 | D3: =IFERROR('Historical FS'!D4,0) -> 11292.27 | E3: =IFERROR('Historical FS'!E4,0) -> 12368.9 | F3: =IFERROR('Historical FS'!F4,0) -> 13350.03 | G3: =IFERROR('Historical FS'!G4,0) -> 14740.59 | H3: =IFERROR('Historical FS'!H4,0) -> 16896.96 | I3: =IFERROR('Historical FS'!I4,0) -> 19126.3 | ... K3: =IFERROR('Historical FS'!K4,0) -> 20201.56
A4: Sales Growth | C4: =C3/B3 -> 1.0949817 | D4: =D3/C3 -> 1.128144 | E4: =E3/D3 -> 1.0953422 | F4: =F3/E3 -> 1.0793223 | G4: =G3/F3 -> 1.1041616 | H4: =H3/G3 -> 1.1462879 | I4: =I3/H3 -> 1.1319373 | J4: =J3/I3 -> 1.2754108 | K4: =K3/J3 -> 0.82814016 | M4: =IFERROR(AVERAGE(C4:K4),0) -> 1.098192 | N4: =IFERROR(MEDIAN(C4:K4),0) -> 1.1041616
A5: EBITDA Growth | C5: =IFERROR('Historical FS'!C16/'Historical FS'!B16-1,0) -> 0.13335748 | D5: =IFERROR('Historical FS'!D16/'Historical FS'!C16-1,0) -> 0.2485631 | E5: =IFERROR('Historical FS'!E16/'Historical FS'!D16-1,0) -> 0.11775065 | F5: =IFERROR('Historical FS'!F16/'Historical FS'!E16-1,0) -> 0.094200719 | G5: =IFERROR('Historical FS'!G16/'Historical FS'!F16-1,0) -> 0.11272841 | H5: =IFERROR('Historical FS'!H16/'Historical FS'!G16-1,0) -> 0.040391309 | I5: =IFERROR('Historical FS'!I16/'Historical FS'!H16-1,0) -> 0.20632492 | J5: =IFERROR('Historical FS'!J16/'Historical FS'!I16-1,0) -> 0.30689624 | K5: =IFERROR('Historical FS'!K16/'Historical FS'!J16-1,0) -> -0.18342769 | M5: =IFERROR(AVERAGE(C5:K5),0) -> 0.11964279 | N5: =IFERROR(MEDIAN(C5:K5),0) -> 0.11775065
A6: EBIT Growth | C6: =IFERROR('Historical FS'!C25/'Historical FS'!B25-1,0) -> 0.1901927 | D6: =IFERROR('Historical FS'!D25/'Historical FS'!C25-1,0) -> 0.32058392 | E6: =IFERROR('Historical FS'!E25/'Historical FS'!D25-1,0) -> 0.10067725 | F6: =IFERROR('Historical FS'!F25/'Historical FS'!E25-1,0) -> 0.052104178 | G6: =IFERROR('Historical FS'!G25/'Historical FS'!F25-1,0) -> 0.015831257 | H6: =IFERROR('Historical FS'!H25/'Historical FS'!G25-1,0) -> 0.13951885 | I6: =IFERROR('Historical FS'!I25/'Historical FS'!H25-1,0) -> 0.24027248 | J6: =IFERROR('Historical FS'!J25/'Historical FS'!I25-1,0) -> 0.30968058 | K6: =IFERROR('Historical FS'!K25/'Historical FS'!J25-1,0) -> -0.1590888 | M6: =IFERROR(AVERAGE(C6:K6),0) -> 0.13441916 | N6: =IFERROR(MEDIAN(C6:K6),0) -> 0.13951885
A7: Net Profit Growth | C7: =IFERROR('Historical FS'!C31/'Historical FS'!B31-1,0) -> 0.223526 | D7: =IFERROR('Historical FS'!D31/'Historical FS'!C31-1,0) -> 0.31157616 | E7: =IFERROR('Historical FS'!E31/'Historical FS'!D31-1,0) -> 0.22496935 | F7: =IFERROR('Historical FS'!F31/'Historical FS'!E31-1,0) -> 0.057908801 | G7: =IFERROR('Historical FS'!G31/'Historical FS'!F31-1,0) -> 0.017277892 | H7: =IFERROR('Historical FS'!H31/'Historical FS'!G31-1,0) -> 0.12845011 | I7: =IFERROR('Historical FS'!I31/'Historical FS'!H31-1,0) -> 0.25440072 | J7: =IFERROR('Historical FS'!J31/'Historical FS'!I31-1,0) -> 0.31152811 | K7: =IFERROR('Historical FS'!K31/'Historical FS'!J31-1,0) -> -0.1572248 | M7: =IFERROR(AVERAGE(C7:K7),0) -> 0.15249026 | N7: =IFERROR(MEDIAN(C7:K7),0) -> 0.223526
A8: Dividend Growth | C8: =IFERROR('Historical FS'!C38/'Historical FS'!B38-1,0) -> 0.36506708 | D8: =IFERROR('Historical FS'!D38/'Historical FS'!C38-1,0) -> 0.33721253 | E8: =IFERROR('Historical FS'!E38/'Historical FS'!D38-1,0) -> 1.9739094 | F8: =IFERROR('Historical FS'!F38/'Historical FS'!E38-1,0) -> -0.41520397 | G8: =IFERROR('Historical FS'!G38/'Historical FS'!F38-1,0) -> 0 | H8: =IFERROR('Historical FS'!H38/'Historical FS'!G38-1,0) -> 0.1 | I8: =IFERROR('Historical FS'!I38/'Historical FS'!H38-1,0) -> -0.20908997 | J8: =IFERROR('Historical FS'!J38/'Historical FS'!I38-1,0) -> 0.85028222 | K8: =IFERROR('Historical FS'!K38/'Historical FS'!J38-1,0) -> -0.1614896 | M8: =IFERROR(AVERAGE(C8:K8),0) -> 0.31563197 | N8: =IFERROR(MEDIAN(C8:K8),0) -> 0.1
A10: Gross Margin | B10: =IFERROR('Historical FS'!B10/'Historical FS'!B4,0) -> 0.43062943 | C10: =IFERROR('Historical FS'!C10/'Historical FS'!C4,0) -> 0.4184423 | D10: =IFERROR('Historical FS'!D10/'Historical FS'!D4,0) -> 0.44728562 | E10: =IFERROR('Historical FS'!E10/'Historical FS'!E4,0) -> 0.4337435 | F10: =IFERROR('Historical FS'!F10/'Historical FS'!F4,0) -> 0.42416609 | G10: =IFERROR('Historical FS'!G10/'Historical FS'!G4,0) -> 0.42192612 | H10: =IFERROR('Historical FS'!H10/'Historical FS'!H4,0) -> 0.39505686 | I10: =IFERROR('Historical FS'!I10/'Historical FS'!I4,0) -> 0.46242138 | ... K10: =IFERROR('Historical FS'!K10/'Historical FS'!K4,0) -> 0.42345393 | M10: =IFERROR(AVERAGE(B10:K10),0) -> 0.42790411 | N10: =IFERROR(MEDIAN(B10:K10),0) -> 0.42381001
A11: EBITDA Margin | B11: =IFERROR('Historical FS'!B17,0) -> 0.20235983 | C11: =IFERROR('Historical FS'!C17,0) -> 0.20945193 | D11: =IFERROR('Historical FS'!D17,0) -> 0.23180902 | E11: =IFERROR('Historical FS'!E17,0) -> 0.23655135 | F11: =IFERROR('Historical FS'!F17,0) -> 0.2398122 | G11: =IFERROR('Historical FS'!G17,0) -> 0.24167282 | H11: =IFERROR('Historical FS'!H17,0) -> 0.21934656 | I11: =IFERROR('Historical FS'!I17,0) -> 0.23376137 | ... K11: =IFERROR('Historical FS'!K17,0) -> 0.23618622 | M11: =IFERROR(AVERAGE(B11:K11),0) -> 0.22904834 | N11: =IFERROR(MEDIAN(B11:K11),0) -> 0.23497379
A12: EBIT Margin | B12: =IFERROR((('Historical FS'!B16-'Historical FS'!B22)/'Historical FS'!B4),0) -> 0.16367075 | C12: =IFERROR((('Historical FS'!C16-'Historical FS'!C22)/'Historical FS'!C4),0) -> 0.17525975 | D12: =IFERROR((('Historical FS'!D16-'Historical FS'!D22)/'Historical FS'!D4),0) -> 0.20208337 | E12: =IFERROR((('Historical FS'!E16-'Historical FS'!E22)/'Historical FS'!E4),0) -> 0.20662549 | F12: =IFERROR((('Historical FS'!F16-'Historical FS'!F22)/'Historical FS'!F4),0) -> 0.21206844 | G12: =IFERROR((('Historical FS'!G16-'Historical FS'!G22)/'Historical FS'!G4),0) -> 0.21514607 | H12: =IFERROR((('Historical FS'!H16-'Historical FS'!H22)/'Historical FS'!H4),0) -> 0.19549552 | I12: =IFERROR((('Historical FS'!I16-'Historical FS'!I22)/'Historical FS'!I4),0) -> 0.21133622 | ... K12: =IFERROR((('Historical FS'!K16-'Historical FS'!K22)/'Historical FS'!K4),0) -> 0.20945957 | M12: =IFERROR(AVERAGE(B12:K12),0) -> 0.2007403 | N12: =IFERROR(MEDIAN(B12:K12),0) -> 0.20804253
A13: EBT Margin | B13: =IFERROR('Historical FS'!B26,0) -> 0.16905399 | C13: =IFERROR('Historical FS'!C26,0) -> 0.1837536 | D13: =IFERROR('Historical FS'!D26,0) -> 0.21509847 | E13: =IFERROR('Historical FS'!E26,0) -> 0.21614614 | F13: =IFERROR('Historical FS'!F26,0) -> 0.21069541 | G13: =IFERROR('Historical FS'!G26,0) -> 0.19384027 | H13: =IFERROR('Historical FS'!H26,0) -> 0.19269561 | I13: =IFERROR('Historical FS'!I26,0) -> 0.21113807 | ... K13: =IFERROR('Historical FS'!K26,0) -> 0.22015478 | M13: =IFERROR(AVERAGE(B13:K13),0) -> 0.20293876 | N13: =IFERROR(MEDIAN(B13:K13),0) -> 0.21091674
A14: Net Profit Margin | B14: =IFERROR('Historical FS'!B32,0) -> 0.10954193 | C14: =IFERROR('Historical FS'!C32,0) -> 0.12240149 | D14: =IFERROR('Historical FS'!D32,0) -> 0.14230354 | E14: =IFERROR('Historical FS'!E32,0) -> 0.15914431 | F14: =IFERROR('Historical FS'!F32,0) -> 0.15598692 | G14: =IFERROR('Historical FS'!G32,0) -> 0.1437127 | H14: =IFERROR('Historical FS'!H32,0) -> 0.14147634 | I14: =IFERROR('Historical FS'!I32,0) -> 0.15678255 | ... K14: =IFERROR('Historical FS'!K32,0) -> 0.16407149 | M14: =IFERROR(AVERAGE(B14:K14),0) -> 0.14566436 | N14: =IFERROR(MEDIAN(B14:K14),0) -> 0.14984981
A16: Sales Expenses % Sales | B16: =IFERROR('Historical FS'!B14,0) -> 0.2282696 | C16: =IFERROR('Historical FS'!C14,0) -> 0.20899037 | D16: =IFERROR('Historical FS'!D14,0) -> 0.2154766 | E16: =IFERROR('Historical FS'!E14,0) -> 0.19719215 | F16: =IFERROR('Historical FS'!F14,0) -> 0.18435389 | G16: =IFERROR('Historical FS'!G14,0) -> 0.1802533 | H16: =IFERROR('Historical FS'!H14,0) -> 0.17571031 | I16: =IFERROR('Historical FS'!I14,0) -> 0.22866001 | ... K16: =IFERROR('Historical FS'!K14,0) -> 0.18726772 | M16: =IFERROR(AVERAGE(B16:K16),0) -> 0.19885577 | N16: =IFERROR(MEDIAN(B16:K16),0) -> 0.19222993
A17: Depriciation % Sales | B17: =IFERROR('Historical FS'!B23,0) -> 0.038689076 | C17: =IFERROR('Historical FS'!C23,0) -> 0.034192176 | D17: =IFERROR('Historical FS'!D23,0) -> 0.029725644 | E17: =IFERROR('Historical FS'!E23,0) -> 0.029925862 | F17: =IFERROR('Historical FS'!F23,0) -> 0.027743758 | G17: =IFERROR('Historical FS'!G23,0) -> 0.026526754 | H17: =IFERROR('Historical FS'!H23,0) -> 0.023851036 | I17: =IFERROR('Historical FS'!I23,0) -> 0.022425142 | ... K17: =IFERROR('Historical FS'!K23,0) -> 0.026726649 | M17: =IFERROR(AVERAGE(B17:K17),0) -> 0.028308037 | N17: =IFERROR(MEDIAN(B17:K17),0) -> 0.027235203
A18: Operating Income % Sales | B18: =IFERROR('Ratio Analysis'!B12,0) -> 0.16367075 | C18: =IFERROR('Ratio Analysis'!C12,0) -> 0.17525975 | D18: =IFERROR('Ratio Analysis'!D12,0) -> 0.20208337 | E18: =IFERROR('Ratio Analysis'!E12,0) -> 0.20662549 | F18: =IFERROR('Ratio Analysis'!F12,0) -> 0.21206844 | G18: =IFERROR('Ratio Analysis'!G12,0) -> 0.21514607 | H18: =IFERROR('Ratio Analysis'!H12,0) -> 0.19549552 | I18: =IFERROR('Ratio Analysis'!I12,0) -> 0.21133622 | ... K18: =IFERROR('Ratio Analysis'!K12,0) -> 0.20945957 | M18: =IFERROR(AVERAGE(B18:K18),0) -> 0.2007403 | N18: =IFERROR(MEDIAN(B18:K18),0) -> 0.20804253
A20: Return on Capital Employed | B20: =IFERROR(('Historical FS'!B16-'Historical FS'!B22)/('Historical FS'!B45+'Historical FS'!B46+ 'Historical FS'!B47),0) -> 0.45126799 | C20: =IFERROR(('Historical FS'!C16-'Historical FS'!C22)/('Historical FS'!C45+'Historical FS'!C46+ 'Historical FS'!C47),0) -> 0.50764383 | D20: =IFERROR(('Historical FS'!D16-'Historical FS'!D22)/('Historical FS'!D45+'Historical FS'!D46+ 'Historical FS'!D47),0) -> 0.61527469 | E20: =IFERROR(('Historical FS'!E16-'Historical FS'!E22)/('Historical FS'!E45+'Historical FS'!E46+ 'Historical FS'!E47),0) -> 1.2125049 | F20: =IFERROR(('Historical FS'!F16-'Historical FS'!F22)/('Historical FS'!F45+'Historical FS'!F46+ 'Historical FS'!F47),0) -> 1.3065723 | G20: =IFERROR(('Historical FS'!G16-'Historical FS'!G22)/('Historical FS'!G45+'Historical FS'!G46+ 'Historical FS'!G47),0) -> 1.4331719 | H20: =IFERROR(('Historical FS'!H16-'Historical FS'!H22)/('Historical FS'!H45+'Historical FS'!H46+ 'Historical FS'!H47),0) -> 1.2101301 | I20: =IFERROR(('Historical FS'!I16-'Historical FS'!I22)/('Historical FS'!I45+'Historical FS'!I46+ 'Historical FS'!I47),0) -> 1.4807835 | ... K20: =IFERROR(('Historical FS'!K16-'Historical FS'!K22)/('Historical FS'!K45+'Historical FS'!K46+ 'Historical FS'!K47),0) -> 0.80079674 | M20: =IFERROR(AVERAGE(B20:K20),0) -> 1.0449562 | N20: =IFERROR(MEDIAN(B20:K20),0) -> 1.2113175
A21: Retained Earning % | B21: =IFERROR('Historical FS'!B41,0) -> 0.39337501 | C21: =IFERROR('Historical FS'!C41,0) -> 0.32319885 | D21: =IFERROR('Historical FS'!D41,0) -> 0.30996994 | E21: =IFERROR('Historical FS'!E41,0) -> -0.67521489 | F21: =IFERROR('Historical FS'!F41,0) -> 0.073966472 | G21: =IFERROR('Historical FS'!G41,0) -> 0.089694629 | H21: =IFERROR('Historical FS'!H41,0) -> 0.11264495 | I21: =IFERROR('Historical FS'!I41,0) -> 0.4405153 | ... K21: =IFERROR('Historical FS'!K41,0) -> 0.21456027 | M21: =IFERROR(AVERAGE(B21:K21),0) -> 0.14932759 | N21: =IFERROR(MEDIAN(B21:K21),0) -> 0.21256283
A22: Return on Equity % | B22: =IFERROR('Historical FS'!B31/SUM('Historical FS'!B45:B46),0) -> 0.30507597 | C22: =IFERROR('Historical FS'!C31/SUM('Historical FS'!C45:C46),0) -> 0.3581809 | D22: =IFERROR('Historical FS'!D31/SUM('Historical FS'!D45:D46),0) -> 0.43740983 | E22: =IFERROR('Historical FS'!E31/SUM('Historical FS'!E45:E46),0) -> 1.0258329 | F22: =IFERROR('Historical FS'!F31/SUM('Historical FS'!F45:F46),0) -> 1.0312429 | G22: =IFERROR('Historical FS'!G31/SUM('Historical FS'!G45:G46),0) -> 1.0883846 | H22: =IFERROR('Historical FS'!H31/SUM('Historical FS'!H45:H46),0) -> 0.97208408 | I22: =IFERROR('Historical FS'!I31/SUM('Historical FS'!I45:I46),0) -> 1.219383 | ... K22: =IFERROR('Historical FS'!K31/SUM('Historical FS'!K45:K46),0) -> 0.80504718 | M22: =IFERROR(AVERAGE(B22:K22),0) -> 0.84198246 | N22: =IFERROR(MEDIAN(B22:K22),0) -> 0.99895849
A23: Self Sustained Growth Rate | B23: =IFERROR(B21*B22,0) -> 0.12000926 | C23: =IFERROR(C21*C22,0) -> 0.11576365 | D23: =IFERROR(D21*D22,0) -> 0.1355839 | E23: =IFERROR(E21*E22,0) -> -0.69265766 | F23: =IFERROR(F21*F22,0) -> 0.076277398 | G23: =IFERROR(G21*G22,0) -> 0.097622253 | H23: =IFERROR(H21*H22,0) -> 0.10950036 | I23: =IFERROR(I21*I22,0) -> 0.53715685 | ... K23: =IFERROR(K21*K22,0) -> 0.17273114 | M23: =IFERROR(AVERAGE(B23:K23),0) -> 0.091986122 | N23: =IFERROR(MEDIAN(B23:K23),0) -> 0.11788646
A24: Interest Coverage Ratio | B24: =IFERROR(('Historical FS'!B16-'Historical FS'!B22)/'Historical FS'!B19,0) -> 16.457705 | C24: =IFERROR(('Historical FS'!C16-'Historical FS'!C22)/'Historical FS'!C19,0) -> 19.08901 | D24: =IFERROR(('Historical FS'!D16-'Historical FS'!D22)/'Historical FS'!D19,0) -> 20.383921 | E24: =IFERROR(('Historical FS'!E16-'Historical FS'!E22)/'Historical FS'!E19,0) -> 19.793448 | F24: =IFERROR(('Historical FS'!F16-'Historical FS'!F22)/'Historical FS'!F19,0) -> 17.244 | G24: =IFERROR(('Historical FS'!G16-'Historical FS'!G22)/'Historical FS'!G19,0) -> 15.724812 | H24: =IFERROR(('Historical FS'!H16-'Historical FS'!H22)/'Historical FS'!H19,0) -> 21.370771 | I24: =IFERROR(('Historical FS'!I16-'Historical FS'!I22)/'Historical FS'!I19,0) -> 33.884483 | ... K24: =IFERROR(('Historical FS'!K16-'Historical FS'!K22)/'Historical FS'!K19,0) -> 31.113309 | M24: =IFERROR(AVERAGE(B24:K24),0) -> 23.132079 | N24: =IFERROR(MEDIAN(B24:K24),0) -> 20.088685
A26: Debtor Turnover Ratio | B26: =IFERROR('Historical FS'!B4/'Historical FS'!B57,0) -> 93.345655 | C26: =IFERROR('Historical FS'!C4/'Historical FS'!C57,0) -> 112.50534 | D26: =IFERROR('Historical FS'!D4/'Historical FS'!D57,0) -> 90.635444 | E26: =IFERROR('Historical FS'!E4/'Historical FS'!E57,0) -> 99.484437 | F26: =IFERROR('Historical FS'!F4/'Historical FS'!F57,0) -> 80.943612 | G26: =IFERROR('Historical FS'!G4/'Historical FS'!G57,0) -> 88.814786 | H26: =IFERROR('Historical FS'!H4/'Historical FS'!H57,0) -> 88.055448 | I26: =IFERROR('Historical FS'!I4/'Historical FS'!I57,0) -> 99.67325 | ... K26: =IFERROR('Historical FS'!K4/'Historical FS'!K57,0) -> 55.628693 | M26: =IFERROR(AVERAGE(B26:K26),0) -> 89.027514 | N26: =IFERROR(MEDIAN(B26:K26),0) -> 89.725115
A27: Creditor Turnover Ratio | B27: =IFERROR('Historical FS'!B4/'Historical FS'!B48,0) -> 2.6155629 | C27: =IFERROR('Historical FS'!C4/'Historical FS'!C48,0) -> 2.5620575 | D27: =IFERROR('Historical FS'!D4/'Historical FS'!D48,0) -> 2.5786148 | E27: =IFERROR('Historical FS'!E4/'Historical FS'!E48,0) -> 2.4419709 | F27: =IFERROR('Historical FS'!F4/'Historical FS'!F48,0) -> 2.3286696 | G27: =IFERROR('Historical FS'!G4/'Historical FS'!G48,0) -> 2.4480784 | H27: =IFERROR('Historical FS'!H4/'Historical FS'!H48,0) -> 2.7039246 | I27: =IFERROR('Historical FS'!I4/'Historical FS'!I48,0) -> 3.0606732 | ... K27: =IFERROR('Historical FS'!K4/'Historical FS'!K48,0) -> 2.8695846 | M27: =IFERROR(AVERAGE(B27:K27),0) -> 2.7176726 | N27: =IFERROR(MEDIAN(B27:K27),0) -> 2.5970889
A28: Inventory Turnover Ratio | B28: =IFERROR('Historical FS'!B4/'Historical FS'!B58,0) -> 9.7242091 | C28: =IFERROR('Historical FS'!C4/'Historical FS'!C58,0) -> 11.091338 | D28: =IFERROR('Historical FS'!D4/'Historical FS'!D58,0) -> 11.695169 | E28: =IFERROR('Historical FS'!E4/'Historical FS'!E58,0) -> 9.640082 | F28: =IFERROR('Historical FS'!F4/'Historical FS'!F58,0) -> 9.4247924 | G28: =IFERROR('Historical FS'!G4/'Historical FS'!G58,0) -> 9.2553857 | H28: =IFERROR('Historical FS'!H4/'Historical FS'!H58,0) -> 8.7604847 | I28: =IFERROR('Historical FS'!I4/'Historical FS'!I58,0) -> 9.9163197 | ... K28: =IFERROR('Historical FS'!K4/'Historical FS'!K58,0) -> 7.0879185 | M28: =IFERROR(AVERAGE(B28:K28),0) -> 9.8270992 | N28: =IFERROR(MEDIAN(B28:K28),0) -> 9.6821455
A29: Fixed Asset Turnover | B29: =IFERROR('Historical FS'!B4/'Historical FS'!B51,0) -> 3.3483045 | C29: =IFERROR('Historical FS'!C4/'Historical FS'!C51,0) -> 3.8260364 | D29: =IFERROR('Historical FS'!D4/'Historical FS'!D51,0) -> 4.7038973 | E29: =IFERROR('Historical FS'!E4/'Historical FS'!E51,0) -> 5.2825813 | F29: =IFERROR('Historical FS'!F4/'Historical FS'!F51,0) -> 6.1255248 | G29: =IFERROR('Historical FS'!G4/'Historical FS'!G51,0) -> 4.9222752 | H29: =IFERROR('Historical FS'!H4/'Historical FS'!H51,0) -> 5.5514538 | I29: =IFERROR('Historical FS'!I4/'Historical FS'!I51,0) -> 6.2838979 | ... K29: =IFERROR('Historical FS'!K4/'Historical FS'!K51,0) -> 3.6907197 | M29: =IFERROR(AVERAGE(B29:K29),0) -> 5.0784439 | N29: =IFERROR(MEDIAN(B29:K29),0) -> 5.1024283
A30: Capital Turnover | B30: =IFERROR('Historical FS'!B4/SUM('Historical FS'!B45:B46),0) -> 2.7850155 | C30: =IFERROR('Historical FS'!C4/SUM('Historical FS'!C45:C46),0) -> 2.9262788 | D30: =IFERROR('Historical FS'!D4/SUM('Historical FS'!D45:D46),0) -> 3.0737804 | E30: =IFERROR('Historical FS'!E4/SUM('Historical FS'!E45:E46),0) -> 6.4459291 | F30: =IFERROR('Historical FS'!F4/SUM('Historical FS'!F45:F46),0) -> 6.6110858 | G30: =IFERROR('Historical FS'!G4/SUM('Historical FS'!G45:G46),0) -> 7.5733361 | H30: =IFERROR('Historical FS'!H4/SUM('Historical FS'!H45:H46),0) -> 6.8710012 | I30: =IFERROR('Historical FS'!I4/SUM('Historical FS'!I45:I46),0) -> 7.7775428 | ... K30: =IFERROR('Historical FS'!K4/SUM('Historical FS'!K45:K46),0) -> 4.9066854 | M30: =IFERROR(AVERAGE(B30:K30),0) -> 5.6272269 | N30: =IFERROR(MEDIAN(B30:K30),0) -> 6.5285075
A32: Debtor Days | B32: =IFERROR(365/B26,0) -> 3.9101981 | C32: =IFERROR(365/'Ratio Analysis'!C26,0) -> 3.2442905 | D32: =IFERROR(365/'Ratio Analysis'!D26,0) -> 4.0271221 | E32: =IFERROR(365/'Ratio Analysis'!E26,0) -> 3.6689156 | F32: =IFERROR(365/'Ratio Analysis'!F26,0) -> 4.509312 | G32: =IFERROR(365/'Ratio Analysis'!G26,0) -> 4.1096761 | H32: =IFERROR(365/'Ratio Analysis'!H26,0) -> 4.1451155 | I32: =IFERROR(365/'Ratio Analysis'!I26,0) -> 3.6619655 | J32: =IFERROR(365/'Ratio Analysis'!J26,0) -> 4.4957118 | K32: =IFERROR(365/'Ratio Analysis'!K26,0) -> 6.5613621 | M32: =IFERROR(AVERAGE(B32:K32),0) -> 4.2333669 | N32: =IFERROR(MEDIAN(B32:K32),0) -> 4.0683991
A33: Payable Days | B33: =IFERROR(365/B27,0) -> 139.54931 | C33: =IFERROR(365/C27,0) -> 142.46362 | D33: =IFERROR(365/D27,0) -> 141.54886 | E33: =IFERROR(365/E27,0) -> 149.46943 | F33: =IFERROR(365/F27,0) -> 156.74186 | G33: =IFERROR(365/G27,0) -> 149.09653 | H33: =IFERROR(365/H27,0) -> 134.98897 | I33: =IFERROR(365/I27,0) -> 119.25481 | ... K33: =IFERROR(365/K27,0) -> 127.19611 | M33: =IFERROR(AVERAGE(B33:K33),0) -> 136.26195 | N33: =IFERROR(MEDIAN(B33:K33),0) -> 140.54909
A34: Inventory Days | B34: =IFERROR(365/B28,0) -> 37.535186 | C34: =IFERROR(365/C28,0) -> 32.908563 | D34: =IFERROR(365/D28,0) -> 31.209469 | E34: =IFERROR(365/E28,0) -> 37.862749 | F34: =IFERROR(365/F28,0) -> 38.727643 | G34: =IFERROR(365/G28,0) -> 39.436498 | H34: =IFERROR(365/H28,0) -> 41.664362 | I34: =IFERROR(365/I28,0) -> 36.80801 | ... K34: =IFERROR(365/K28,0) -> 51.496078 | M34: =IFERROR(AVERAGE(B34:K34),0) -> 37.891116 | N34: =IFERROR(MEDIAN(B34:K34),0) -> 37.698967
A35: Cash Conversion Cycle | B35: =SUM(B32,B34-B33) -> -98.103927 | C35: =SUM(C32,C34-C33) -> -106.31077 | D35: =SUM(D32,D34-D33) -> -106.31227 | E35: =SUM(E32,E34-E33) -> -107.93777 | F35: =SUM(F32,F34-F33) -> -113.5049 | G35: =SUM(G32,G34-G33) -> -105.55036 | H35: =SUM(H32,H34-H33) -> -89.179494 | I35: =SUM(I32,I34-I33) -> -78.784833 | ... K35: =SUM(K32,K34-K33) -> -69.13867 | M35: =IFERROR(AVERAGE(B35:K35),0) -> -94.137467 | N35: =IFERROR(MEDIAN(B35:K35),0) -> -101.82714
A37: CFO/SALES | B37: =IFERROR('Historical FS'!B77/'Historical FS'!B4,0) -> 0.16047975 | C37: =IFERROR('Historical FS'!C77/'Historical FS'!C4,0) -> 0.18162564 | D37: =IFERROR('Historical FS'!D77/'Historical FS'!D4,0) -> 0.18180578 | E37: =IFERROR('Historical FS'!E77/'Historical FS'!E4,0) -> 0.18546516 | F37: =IFERROR('Historical FS'!F77/'Historical FS'!F4,0) -> 0.18389472 | G37: =IFERROR('Historical FS'!G77/'Historical FS'!G4,0) -> 0.15155431 | H37: =IFERROR('Historical FS'!H77/'Historical FS'!H4,0) -> 0.1619818 | I37: =IFERROR('Historical FS'!I77/'Historical FS'!I4,0) -> 0.17739971 | ... K37: =IFERROR('Historical FS'!K77/'Historical FS'!K4,0) -> 0.14538481 | M37: =IFERROR(AVERAGE(B37:K37),0) -> 0.17007001 | N37: =IFERROR(MEDIAN(B37:K37),0) -> 0.17425406
A38: CFO/TOTAL ASSETS | B38: =IFERROR('Historical FS'!B77/'Historical FS'!B62,0) -> 0.21540395 | C38: =IFERROR('Historical FS'!C77/'Historical FS'!C62,0) -> 0.24692398 | D38: =IFERROR('Historical FS'!D77/'Historical FS'!D62,0) -> 0.25383033 | E38: =IFERROR('Historical FS'!E77/'Historical FS'!E62,0) -> 0.31981308 | F38: =IFERROR('Historical FS'!F77/'Historical FS'!F62,0) -> 0.31077011 | G38: =IFERROR('Historical FS'!G77/'Historical FS'!G62,0) -> 0.27130978 | H38: =IFERROR('Historical FS'!H77/'Historical FS'!H62,0) -> 0.30483119 | I38: =IFERROR('Historical FS'!I77/'Historical FS'!I62,0) -> 0.37789267 | ... K38: =IFERROR('Historical FS'!K77/'Historical FS'!K62,0) -> 0.23831761 | M38: =IFERROR(AVERAGE(B38:K38),0) -> 0.29357454 | N38: =IFERROR(MEDIAN(B38:K38),0) -> 0.28807049
A39: CFO/TOTAL DEBT | B39: =IFERROR('Historical FS'!B77/'Historical FS'!B47,0) -> 44.253394 | C39: =IFERROR('Historical FS'!C77/'Historical FS'!C47,0) -> 51.735913 | D39: =IFERROR('Historical FS'!D77/'Historical FS'!D47,0) -> 58.423449 | E39: =IFERROR('Historical FS'!E77/'Historical FS'!E47,0) -> 12.141421 | F39: =IFERROR('Historical FS'!F77/'Historical FS'!F47,0) -> 16.645196 | G39: =IFERROR('Historical FS'!G77/'Historical FS'!G47,0) -> 8.3839976 | H39: =IFERROR('Historical FS'!H77/'Historical FS'!H47,0) -> 10.117551 | I39: =IFERROR('Historical FS'!I77/'Historical FS'!I47,0) -> 12.542511 | ... K39: =IFERROR('Historical FS'!K77/'Historical FS'!K47,0) -> 2.517033 | M39: =IFERROR(AVERAGE(B39:K39),0) -> 22.887552 | N39: =IFERROR(MEDIAN(B39:K39),0) -> 12.341966

Sheet Forecating
D3: 41791 | E3: 42156 | F3: Mar 2016 9m | G3: 42795 | H3: 43160 | I3: 43525 | J3: 43891 | K3: 44256 | L3: 44621 | M3: 44986 | N3: 45352 | O3: 45717
C4: Sales + | D4: 32144 | E4: 36701 | F4: 31136 | G4: 47568 | H4: 50569 | I4: 60427 | J4: 70676 | K4: 75379 | L4: 85651 | M4: 101456 | N4: 109913 | O4: 117055
B8: Year weight | C8: year | D8: Sales | E8: sales Growth
B9: 1 | C9: =D3 -> 41791 | D9: 32144
B10: 2 | C10: =C9+365 -> 42156 | D10: 36701 | E10: =D10/D9-1 -> 0.14176829
B11: 3 | C11: =C10+365 -> 42521 | D11: 31136 | E11: =D11/D10-1 -> -0.15163075
B12: 4 | C12: =C11+365 -> 42886 | D12: 47568 | E12: =D12/D11-1 -> 0.52774923
B13: 5 | C13: =C12+365 -> 43251 | D13: 50569 | E13: =D13/D12-1 -> 0.063088631 | H13: SUMMARY OUTPUT
B14: 6 | C14: =C13+365 -> 43616 | D14: 60427 | E14: =D14/D13-1 -> 0.19494156
B15: 7 | C15: =C14+365 -> 43981 | D15: 70676 | E15: =D15/D14-1 -> 0.16960961 | H15: Regression Statistics
B16: 8 | C16: =C15+365 -> 44346 | D16: 75379 | E16: =D16/D15-1 -> 0.066543098 | H16: Multiple R | I16: 0.98860795
B17: 9 | C17: =C16+365 -> 44711 | D17: 85651 | E17: =D17/D16-1 -> 0.13627138 | H17: R Square | I17: 0.97734568
B18: 10 | C18: =C17+365 -> 45076 | D18: 101456 | E18: =D18/D17-1 -> 0.18452791 | H18: Adjusted R Square | I18: 0.97482854
B19: 11 | C19: =C18+365 -> 45441 | D19: 109913 | E19: =D19/D18-1 -> 0.083356332 | H19: Standard Error | I19: 4662.9066
B20: 12 | C20: =C19+365 -> 45806 | D20: 117055 | E20: =D20/D19-1 -> 0.064978665 | H20: Observations | I20: 11
B21: 13 | C21: =C20+365 -> 46171 | D21: =$J$29+(B21*$J$30) -> 9194.6451 | E21: =D21/D20-1 -> -0.92145022
B22: 14 | C22: =C21+365 -> 46536 | D22: =$J$29+(B22*$J$30) -> 9639.2358 | E22: =D22/D21-1 -> 0.04835322 | H22: ANOVA
B23: 15 | C23: =C22+365 -> 46901 | D23: =$J$29+(B23*$J$30) -> 10083.826 | E23: =D23/D22-1 -> 0.046123024 | I23: df | J23: SS | K23: MS | L23: F | M23: Significance F
B24: 16 | C24: =C23+365 -> 47266 | D24: =$J$29+(B24*$J$30) -> 10528.417 | E24: =D24/D23-1 -> 0.044089483 | H24: Regression | I24: 1 | J24: 8.4421522e+09 | K24: 8.4421522e+09 | L24: 388.27528 | M24: 1.0351982e-08
B25: 17 | C25: =C24+365 -> 47631 | D25: =$J$29+(B25*$J$30) -> 10973.008 | E25: =D25/D24-1 -> 0.042227687 | H25: Residual | I25: 9 | J25: 1.9568428e+08 | K25: 21742698
H26: Total | I26: 10 | J26: 8.6378365e+09
I28: Coefficients | J28: Standard Error | K28: t Stat | L28: P-value | M28: Lower 95% | N28: Upper 95% | O28: Lower 95.0% | P28: Upper 95.0%
H29: Intercept | I29: 10179.127 | J29: 3414.966 | K29: 2.9807405 | L29: 0.015431027 | M29: 2453.9376 | N29: 17904.317 | O29: 2453.9376 | P29: 17904.317
H30: 1 | I30: 8760.5273 | J30: 444.5907 | K30: 19.704702 | L30: 1.0351982e-08 | M30: 7754.7932 | N30: 9766.2613 | O30: 7754.7932 | P30: 9766.2613
B31: Arithmetic Mean | C31: =AVERAGE(E10:E20) -> 0.13465491
B32: Gemotric Mean | C32: =_xlfn.RRI(B20,D9,D20) -> 0.11371526
B33: Standard deviation | C33: =_xlfn.STDEV.S(E10:E20) -> 0.16159416
H35: =FORECAST(B21,$D$19:$E$20,C9:C20) -> #N/A
B39: 13 | C39: =C38+365 -> 365 | D39: =$J$29+(B39*$J$30) -> 9194.6451
B40: 14 | C40: =C39+365 -> 730 | D40: =$J$29+(B40*$J$30) -> 9639.2358 | E40: =D40/D39-1 -> 0.04835322
B41: 15 | C41: =C40+365 -> 1095 | D41: =$J$29+(B41*$J$30) -> 10083.826 | E41: =D41/D40-1 -> 0.046123024
B42: 16 | C42: =C41+365 -> 1460 | D42: =$J$29+(B42*$J$30) -> 10528.417 | E42: =D42/D41-1 -> 0.044089483
B43: 17 | C43: =C42+365 -> 1825 | D43: =$J$29+(B43*$J$30) -> 10973.008 | E43: =D43/D42-1 -> 0.042227687

Sheet % Change
B2: NESTLE LTD | F2: NIFTY50
A3: Date | B3: Price | C3: Change % | D3: Return | F3: Price | G3: Change % | H3: Return
A4: Apr 19, 2026 | B4: 1413.1 | C4: 0.0992 | F4: 23960.25 | G4: -0.0161
A5: Apr 12, 2026 | B5: 1285.6 | C5: 0.0291 | D5: =B5/B4-1 -> -0.09022716 | F5: 24353.55 | G5: 0.0126 | H5: =F5/F4-1 -> 0.016414687
A6: Apr 05, 2026 | B6: 1249.3 | C6: 0.0487 | D6: =B6/B5-1 -> -0.028235843 | F6: 24050.6 | G6: 0.0589 | H6: =F6/F5-1 -> -0.012439665
A7: Mar 29, 2026 | B7: 1191.3 | C7: -0.0016 | D7: =B7/B6-1 -> -0.046425999 | F7: 22713.1 | G7: -0.0047 | H7: =F7/F6-1 -> -0.055611918 | I7: Average Return | J7: =AVERAGE(G4:G107) -> 0.0008125
A8: Mar 22, 2026 | B8: 1193.2 | C8: -0.0003 | D8: =B8/B7-1 -> 0.0015948963 | F8: 22819.6 | G8: -0.0128 | H8: =F8/F7-1 -> 0.004688924 | I8: Dividend Yield | J8: 0.0128
A9: Mar 15, 2026 | B9: 1193.6 | C9: -0.0072 | D9: =B9/B8-1 -> 0.00033523299 | F9: 23114.5 | G9: -0.0016 | H9: =F9/F8-1 -> 0.012923101 | I9: Market return | J9: =SUM(J7:J8) -> 0.0136125 | L9: SUMMARY OUTPUT
A10: Mar 08, 2026 | B10: 1202.2 | C10: -0.0401 | D10: =B10/B9-1 -> 0.0072050938 | F10: 23151.1 | G10: -0.0531 | H10: =F10/F9-1 -> 0.0015834217
A11: Mar 01, 2026 | B11: 1252.4 | C11: -0.0304 | D11: =B11/B10-1 -> 0.041756779 | F11: 24450.45 | G11: -0.0289 | H11: =F11/F10-1 -> 0.056124763 | L11: Regression Statistics
A12: Feb 22, 2026 | B12: 1291.7 | C12: -0.0016 | D12: =B12/B11-1 -> 0.031379751 | F12: 25178.65 | G12: -0.0154 | H12: =F12/F11-1 -> 0.029782683 | L12: Multiple R | M12: 0.48585255
A13: Feb 15, 2026 | B13: 1293.8 | C13: 0.0087 | D13: =B13/B12-1 -> 0.0016257645 | F13: 25571.25 | G13: 0.0039 | H13: =F13/F12-1 -> 0.015592575 | L13: R Square | M13: 0.2360527
A14: Feb 08, 2026 | B14: 1282.6 | C14: -0.0159 | D14: =B14/B13-1 -> -0.0086566703 | F14: 25471.1 | G14: -0.0087 | H14: =F14/F13-1 -> -0.0039165078 | L14: Adjusted R Square | M14: 0.22848887
A15: Feb 01, 2026 | B15: 1303.3 | C15: -0.0218 | D15: =B15/B14-1 -> 0.016139092 | F15: 25693.7 | G15: 0.0147 | H15: =F15/F14-1 -> 0.0087393163 | L15: Standard Error | M15: 0.025674912
A16: Jan 25, 2026 | B16: 1332.4 | C16: 0.0298 | D16: =B16/B15-1 -> 0.022327937 | F16: 25320.65 | G16: 0.0109 | H16: =F16/F15-1 -> -0.014519123 | L16: Observations | M16: 103
A17: Jan 18, 2026 | B17: 1293.8 | C17: -0.0168 | D17: =B17/B16-1 -> -0.028970279 | F17: 25048.65 | G17: -0.0251 | H17: =F17/F16-1 -> -0.01074222
A18: Jan 11, 2026 | B18: 1315.9 | C18: 0.0129 | D18: =B18/B17-1 -> 0.017081465 | F18: 25694.35 | G18: 0.0004 | H18: =F18/F17-1 -> 0.025777836 | L18: ANOVA
A19: Jan 04, 2026 | B19: 1299.1 | C19: 0.0152 | D19: =B19/B18-1 -> -0.012766928 | F19: 25683.3 | G19: -0.0245 | H19: =F19/F18-1 -> -0.00043005563 | M19: df | N19: SS | O19: MS | P19: F | Q19: Significance F
A20: Dec 28, 2025 | B20: 1279.7 | C20: 0.0056 | D20: =B20/B19-1 -> -0.014933415 | F20: 26328.55 | G20: 0.011 | H20: =F20/F19-1 -> 0.025123329 | L20: Regression | M20: 1 | N20: 0.020572395 | O20: 0.020572395 | P20: 31.208073 | Q20: 1.9686732e-07
A21: Dec 21, 2025 | B21: 1272.6 | C21: 0.0227 | D21: =B21/B20-1 -> -0.0055481754 | F21: 26042.3 | G21: 0.0029 | H21: =F21/F20-1 -> -0.010872228 | L21: Residual | M21: 101 | N21: 0.066579309 | O21: 0.00065920108
A22: Dec 14, 2025 | B22: 1244.4 | C22: 0.0049 | D22: =B22/B21-1 -> -0.022159359 | F22: 25966.4 | G22: -0.0031 | H22: =F22/F21-1 -> -0.0029144891 | L22: Total | M22: 102 | N22: 0.087151705
A23: Dec 07, 2025 | B23: 1238.3 | C23: -0.0069 | D23: =B23/B22-1 -> -0.0049019608 | F23: 26046.95 | G23: -0.0053 | H23: =F23/F22-1 -> 0.0031020858
A24: Nov 30, 2025 | B24: 1246.9 | C24: -0.0113 | D24: =B24/B23-1 -> 0.0069450052 | F24: 26186.45 | G24: -0.0006 | H24: =F24/F23-1 -> 0.0053557134 | M24: Coefficients | N24: Standard Error | O24: t Stat | P24: P-value | Q24: Lower 95% | R24: Upper 95% | S24: Lower 95.0% | T24: Upper 95.0%
A25: Nov 23, 2025 | B25: 1261.1 | C25: -0.0153 | D25: =B25/B24-1 -> 0.011388243 | F25: 26202.95 | G25: 0.0052 | H25: =F25/F24-1 -> 0.00063009686 | L25: Intercept | M25: -0.00060008713 | N25: 0.0025305439 | O25: -0.2371376 | P25: 0.81303037 | Q25: -0.0056200056 | R25: 0.0044198313 | S25: -0.0056200056 | T25: 0.0044198313
A26: Nov 16, 2025 | B26: 1280.7 | C26: 0.0072 | D26: =B26/B25-1 -> 0.015541987 | F26: 26068.15 | G26: 0.0061 | H26: =F26/F25-1 -> -0.0051444589 | L26: X Variable 1 | M26: 0.75565254 | N26: 0.13526601 | O26: 5.5864186 | P26: 1.9686732e-07 | Q26: 0.48732117 | R26: 1.0239839 | S26: 0.48732117 | T26: 1.0239839
A27: Nov 09, 2025 | B27: 1271.6 | C27: 0.007 | D27: =B27/B26-1 -> -0.0071054892 | F27: 25910.05 | G27: 0.0164 | H27: =F27/F26-1 -> -0.0060648723
A28: Nov 02, 2025 | B28: 1262.7 | C28: -0.007 | D28: =B28/B27-1 -> -0.0069990563 | F28: 25492.3 | G28: -0.0089 | H28: =F28/F27-1 -> -0.016123087
A29: Oct 26, 2025 | B29: 1271.6 | C29: -0.0081 | D29: =B29/B28-1 -> 0.0070483884 | F29: 25722.1 | G29: -0.0028 | H29: =F29/F28-1 -> 0.0090144867
A30: Oct 19, 2025 | B30: 1282 | C30: -0.0058 | D30: =B30/B29-1 -> 0.0081786725 | F30: 25795.15 | G30: 0.0033 | H30: =F30/F29-1 -> 0.0028399703 | J30: slope | L30: =SLOPE(D5:D107,H5:H107) -> 0.75565254
A31: Oct 12, 2025 | B31: 1289.5 | C31: 0.075 | D31: =B31/B30-1 -> 0.005850234 | F31: 25709.85 | G31: 0.0168 | H31: =F31/F30-1 -> -0.0033068232
A32: Oct 05, 2025 | B32: 1199.5 | C32: 0.0253 | D32: =B32/B31-1 -> -0.069794494 | F32: 25285.35 | G32: 0.0157 | H32: =F32/F31-1 -> -0.016511182
A33: Sep 28, 2025 | B33: 1169.9 | C33: 0.0063 | D33: =B33/B32-1 -> -0.024676949 | F33: 24894.25 | G33: 0.0097 | H33: =F33/F32-1 -> -0.015467454
A34: Sep 21, 2025 | B34: 1162.6 | C34: -0.0267 | D34: =B34/B33-1 -> -0.0062398496 | F34: 24654.7 | G34: -0.0265 | H34: =F34/F33-1 -> -0.009622704
A35: Sep 14, 2025 | B35: 1194.5 | C35: -0.019 | D35: =B35/B34-1 -> 0.0274385 | F35: 25327.05 | G35: 0.0085 | H35: =F35/F34-1 -> 0.027270662
A36: Sep 07, 2025 | B36: 1217.6 | C36: 0.0075 | D36: =B36/B35-1 -> 0.019338635 | F36: 25114 | G36: 0.0151 | H36: =F36/F35-1 -> -0.0084119548
A37: Aug 31, 2025 | B37: 1208.5 | C37: 0.0452 | D37: =B37/B36-1 -> -0.0074737188 | F37: 24741 | G37: 0.0129 | H37: =F37/F36-1 -> -0.014852274
A38: Aug 24, 2025 | B38: 1156.2 | C38: -0.0058 | D38: =B38/B37-1 -> -0.043276789 | F38: 24426.85 | G38: -0.0178 | H38: =F38/F37-1 -> -0.012697547
A39: Aug 17, 2025 | B39: 1162.9 | C39: 0.0675 | D39: =B39/B38-1 -> 0.0057948452 | F39: 24870.1 | G39: 0.0097 | H39: =F39/F38-1 -> 0.018146016
A40: Aug 10, 2025 | B40: 1089.4 | C40: -0.0065 | D40: =B40/B39-1 -> -0.063204059 | F40: 24631.3 | G40: 0.011 | H40: =F40/F39-1 -> -0.0096018914
A41: Aug 03, 2025 | B41: 1096.5 | C41: -0.0367 | D41: =B41/B40-1 -> 0.006517349 | F41: 24363.3 | G41: -0.0082 | H41: =F41/F40-1 -> -0.010880465
A42: Jul 27, 2025 | B42: 1138.25 | C42: 0.0008 | D42: =B42/B41-1 -> 0.038075695 | F42: 24565.35 | G42: -0.0109 | H42: =F42/F41-1 -> 0.0082932115
... A107: Apr 28, 2024 | B107: 1228.05 | C107: -0.0107 | D107: =B107/B106-1 -> -0.030435812 | F107: 22475.85 | G107: 0.0025 | H107: =F107/F106-1 -> 0.0190726

Sheet Beta-Regression
H1: Peer comparison | P1: BRITANNIA INDS. | AE1: BIKAJI FOODS | AS1: Zydus Wellnes | BH1: Gopal Snacks Ltd
P2: Date | Q2: Price | R2: Change % | S2: Reurn | AE2: Date | AF2: Price | AG2: Change % | AH2: Return | AS2: Date | AT2: Price | AU2: Change % | AV2: Return | BH2: Date | BI2: Price | BJ2: Change % | BK2: Return
C3: S.No. | D3: Name | E3: CMP Rs. | F3: P/E | G3: Mar Cap Rs.Cr. | H3: Div Yld % | I3: NP Qtr Rs.Cr. | J3: Qtr Profit Var % | K3: Sales Qtr Rs.Cr. | L3: Qtr Sales Var % | M3: ROCE % | P3: Apr 19, 2026 | Q3: 5730.5 | R3: -0.0009 | AE3: Apr 19, 2026 | AF3: 659.3 | AG3: -0.0011 | AS3: Apr 19, 2026 | AT3: 490.85 | AU3: -0.0168 | BH3: Apr 19, 2026 | BI3: 275 | BJ3: -0.0305
C4: 1 | D4: Nestle India | E4: 1419 | F4: 79.28 | G4: 273627.85 | H4: 0.95 | I4: 1114.11 | J4: 28.84 | K4: 6747.79 | L4: 22.6 | M4: 84.21 | P4: Apr 12, 2026 | Q4: 5735.5 | R4: 0.032 | S4: =Q4/Q3-1 -> 0.00087252421 | AE4: Apr 12, 2026 | AF4: 660.05 | AG4: 0.0304 | AH4: =AF4/AF3-1 -> 0.0011375702 | AS4: Apr 12, 2026 | AT4: 499.25 | AU4: 0.0194 | AV4: =AT4/AT3-1 -> 0.017113171 | BH4: Apr 12, 2026 | BI4: 283.65 | BJ4: 0.0706 | BK4: =BI4/BI3-1 -> 0.031454545
C5: 2 | D5: Britannia Inds. | E5: 5692 | F5: 56.78 | G5: 137102.24 | H5: 1.31 | I5: 682.14 | J5: 16.89 | K5: 4969.82 | L5: 8.21 | M5: 52.99 | P5: Apr 05, 2026 | Q5: 5557.5 | R5: 0.0212 | S5: =Q5/Q4-1 -> -0.031034783 | AE5: Apr 05, 2026 | AF5: 640.6 | AG5: 0.0217 | AH5: =AF5/AF4-1 -> -0.029467465 | AS5: Apr 05, 2026 | AT5: 489.75 | AU5: 0.1054 | AV5: =AT5/AT4-1 -> -0.019028543 | BH5: Apr 05, 2026 | BI5: 264.95 | BJ5: 0.0142 | BK5: =BI5/BI4-1 -> -0.065926318
C6: 3 | D6: Bikaji Foods | E6: 677.8 | F6: 68.06 | G6: 16994.87 | H6: 0.14 | I6: 62.17 | J6: 117.64 | K6: 790.01 | L6: 10.51 | M6: 18.16 | P6: Mar 29, 2026 | Q6: 5442 | R6: -0.0105 | S6: =Q6/Q5-1 -> -0.020782726 | AE6: Mar 29, 2026 | AF6: 627 | AG6: 0.0162 | AH6: =AF6/AF5-1 -> -0.021230097 | AS6: Mar 29, 2026 | AT6: 443.05 | AU6: -0.0068 | AV6: =AT6/AT5-1 -> -0.095354773 | BH6: Mar 29, 2026 | BI6: 261.25 | BJ6: 0.0402 | BK6: =BI6/BI5-1 -> -0.013964899
C7: 4 | D7: Zydus Wellness | E7: 496.7 | F7: 65.74 | G7: 15803.02 | H7: 0.24 | I7: -39.9 | J7: -643.12 | K7: 964.9 | L7: 108.9 | M7: 6.16 | P7: Mar 22, 2026 | Q7: 5500 | R7: -0.0211 | S7: =Q7/Q6-1 -> 0.010657846 | U7: SUMMARY OUTPUT | AE7: Mar 22, 2026 | AF7: 617 | AG7: -0.0202 | AH7: =AF7/AF6-1 -> -0.015948963 | AS7: Mar 22, 2026 | AT7: 446.1 | AU7: 0.0505 | AV7: =AT7/AT6-1 -> 0.0068840989 | BH7: Mar 22, 2026 | BI7: 251.15 | BJ7: -0.0804 | BK7: =BI7/BI6-1 -> -0.038660287
B8: Not In NSE | C8: 5 | D8: The Bombay Burmah | E8: 1515.1 | F8: 9.73 | G8: 10571.15 | H8: 1.11 | I8: 654.82 | J8: -9.43 | K8: 5065.89 | L8: 8.13 | M8: 35.52 | P8: Mar 15, 2026 | Q8: 5618.5 | R8: -0.0327 | S8: =Q8/Q7-1 -> 0.021545455 | AE8: Mar 15, 2026 | AF8: 629.7 | AG8: 0.0435 | AH8: =AF8/AF7-1 -> 0.020583468 | AI8: SUMMARY OUTPUT | AS8: Mar 15, 2026 | AT8: 424.65 | AU8: 0.0505 | AV8: =AT8/AT7-1 -> -0.048083389 | AW8: SUMMARY OUTPUT | BH8: Mar 15, 2026 | BI8: 273.1 | BJ8: 0.0137 | BK8: =BI8/BI7-1 -> 0.087397969
B9: Not In NSE | C9: 6 | D9: Mrs Bectors | E9: 197.05 | F9: 51.43 | G9: 6049.25 | H9: 0.6 | I9: 33.14 | J9: 21.13 | K9: 496.65 | L9: 8.54 | M9: 16.39 | P9: Mar 08, 2026 | Q9: 5808.5 | R9: -0.0292 | S9: =Q9/Q8-1 -> 0.033816855 | U9: Regression Statistics | AE9: Mar 08, 2026 | AF9: 603.45 | AG9: -0.0177 | AH9: =AF9/AF8-1 -> -0.041686517 | AS9: Mar 08, 2026 | AT9: 404.25 | AU9: 0.0605 | AV9: =AT9/AT8-1 -> -0.048039562 | BH9: Mar 08, 2026 | BI9: 269.4 | BJ9: -0.0834 | BK9: =BI9/BI8-1 -> -0.013548151 | BL9: SUMMARY OUTPUT
C10: 7 | D10: Gopal Snacks | E10: 276.55 | F10: 97.35 | G10: 3446.45 | H10: 0.36 | I10: 15.49 | J10: 190.04 | K10: 400.76 | L10: 1.83 | M10: 16.31 | P10: Mar 01, 2026 | Q10: 5983 | R10: -0.0032 | S10: =Q10/Q9-1 -> 0.03004218 | U10: Multiple R | V10: 0.32251589 | AE10: Mar 01, 2026 | AF10: 614.35 | AG10: -0.0373 | AH10: =AF10/AF9-1 -> 0.018062806 | AI10: Regression Statistics | AS10: Mar 01, 2026 | AT10: 381.2 | AU10: -0.0096 | AV10: =AT10/AT9-1 -> -0.057019171 | AW10: Regression Statistics | BH10: Mar 01, 2026 | BI10: 293.9 | BJ10: -0.0154 | BK10: =BI10/BI9-1 -> 0.090942836
D11: Median: 25 Co. | E11: 246.9 | F11: 56.78 | G11: 612.57 | H11: 0.05 | I11: 3.19 | J11: 16.89 | K11: 176.99 | L11: 8.7 | M11: 16.31 | P11: Feb 22, 2026 | Q11: 6002.5 | R11: -0.0157 | S11: =Q11/Q10-1 -> 0.0032592345 | U11: R Square | V11: 0.1040165 | AE11: Feb 22, 2026 | AF11: 638.15 | AG11: 0.0044 | AH11: =AF11/AF10-1 -> 0.038740132 | AI11: Multiple R | AJ11: 0.38573001 | AS11: Feb 22, 2026 | AT11: 384.9 | AU11: -0.0359 | AV11: =AT11/AT10-1 -> 0.009706191 | AW11: Multiple R | AX11: 0.33541326 | BH11: Feb 22, 2026 | BI11: 298.5 | BJ11: -0.0419 | BK11: =BI11/BI10-1 -> 0.015651582 | BL11: Regression Statistics
P12: Feb 15, 2026 | Q12: 6098.5 | R12: 0.0197 | S12: =Q12/Q11-1 -> 0.015993336 | U12: Adjusted R Square | V12: 0.095056662 | AE12: Feb 15, 2026 | AF12: 635.35 | AG12: -0.0069 | AH12: =AF12/AF11-1 -> -0.0043876831 | AI12: R Square | AJ12: 0.14878764 | AS12: Feb 15, 2026 | AT12: 399.25 | AU12: -0.0198 | AV12: =AT12/AT11-1 -> 0.037282411 | AW12: R Square | AX12: 0.11250206 | BH12: Feb 15, 2026 | BI12: 311.55 | BJ12: 0.0404 | BK12: =BI12/BI11-1 -> 0.043718593 | BL12: Multiple R | BM12: 0.3532729
P13: Feb 08, 2026 | Q13: 5980.5 | R13: 0.0118 | S13: =Q13/Q12-1 -> -0.01934902 | U13: Standard Error | V13: 0.029852361 | AE13: Feb 08, 2026 | AF13: 639.75 | AG13: -0.0154 | AH13: =AF13/AF12-1 -> 0.0069253168 | AI13: Adjusted R Square | AJ13: 0.14027552 | AS13: Feb 08, 2026 | AT13: 407.3 | AU13: 0.0481 | AV13: =AT13/AT12-1 -> 0.020162805 | AW13: Adjusted R Square | AX13: 0.10362708 | BH13: Feb 08, 2026 | BI13: 299.45 | BJ13: -0.0033 | BK13: =BI13/BI12-1 -> -0.038838068 | BL13: R Square | BM13: 0.12480174
E14: Beta | P14: Feb 01, 2026 | Q14: 5911 | R14: 0.0086 | S14: =Q14/Q13-1 -> -0.011621102 | U14: Observations | V14: 102 | AE14: Feb 01, 2026 | AF14: 649.75 | AG14: -0.0123 | AH14: =AF14/AF13-1 -> 0.015631106 | AI14: Standard Error | AJ14: 0.04174926 | AS14: Feb 01, 2026 | AT14: 388.6 | AU14: -0.1332 | AV14: =AT14/AT13-1 -> -0.045912104 | AW14: Standard Error | AX14: 0.044684253 | BH14: Feb 01, 2026 | BI14: 300.45 | BJ14: 0.0012 | BK14: =BI14/BI13-1 -> 0.0033394557 | BL14: Adjusted R Square | BM14: 0.11604976
D15: Nestle India | E15: =SLOPE('% Change'!D5:D107,'% Change'!H5:H107) -> 0.75565254 | P15: Jan 25, 2026 | Q15: 5860.5 | R15: 0.0044 | S15: =Q15/Q14-1 -> -0.0085433937 | AE15: Jan 25, 2026 | AF15: 657.85 | AG15: 0.0107 | AH15: =AF15/AF14-1 -> 0.012466333 | AI15: Observations | AJ15: 102 | AS15: Jan 25, 2026 | AT15: 448.3 | AU15: 0.0711 | AV15: =AT15/AT14-1 -> 0.15362841 | AW15: Observations | AX15: 102 | BH15: Jan 25, 2026 | BI15: 300.1 | BJ15: 0.0139 | BK15: =BI15/BI14-1 -> -0.0011649193 | BL15: Standard Error | BM15: 0.047867878
D16: Britannia Inds. | E16: =SLOPE(S4:S106,'% Change'!H5:H107) -> 0.53478667 | P16: Jan 18, 2026 | Q16: 5835 | R16: -0.0108 | S16: =Q16/Q15-1 -> -0.0043511646 | U16: ANOVA | AE16: Jan 18, 2026 | AF16: 650.9 | AG16: -0.0697 | AH16: =AF16/AF15-1 -> -0.010564718 | AS16: Jan 18, 2026 | AT16: 418.55 | AU16: -0.0481 | AV16: =AT16/AT15-1 -> -0.066361811 | BH16: Jan 18, 2026 | BI16: 296 | BJ16: -0.0746 | BK16: =BI16/BI15-1 -> -0.013662113 | BL16: Observations | BM16: 102
D17: Bikaji Foods | E17: =SLOPE(AH4:AH106,'% Change'!H5:H107) -> 0.91697348 | P17: Jan 11, 2026 | Q17: 5898.5 | R17: -0.0132 | S17: =Q17/Q16-1 -> 0.010882605 | V17: df | W17: SS | X17: MS | Y17: F | Z17: Significance F | AE17: Jan 11, 2026 | AF17: 699.7 | AG17: -0.0034 | AH17: =AF17/AF16-1 -> 0.074973114 | AI17: ANOVA | AS17: Jan 11, 2026 | AT17: 439.7 | AU17: -0.0116 | AV17: =AT17/AT16-1 -> 0.050531597 | AW17: ANOVA | BH17: Jan 11, 2026 | BI17: 319.85 | BJ17: -0.0048 | BK17: =BI17/BI16-1 -> 0.080574324
D18: Zydus Wellness | E18: =SLOPE(AV4:AV106,'% Change'!H5:H107) -> 0.84414186 | P18: Jan 04, 2026 | Q18: 5977.5 | R18: -0.0012 | S18: =Q18/Q17-1 -> 0.013393236 | U18: Regression | V18: 1 | W18: 0.010345693 | X18: 0.010345693 | Y18: 11.609198 | Z18: 0.00094667939 | AE18: Jan 04, 2026 | AF18: 702.1 | AG18: -0.0455 | AH18: =AF18/AF17-1 -> 0.0034300414 | AJ18: df | AK18: SS | AL18: MS | AM18: F | AN18: Significance F | AS18: Jan 04, 2026 | AT18: 444.85 | AU18: -0.0565 | AV18: =AT18/AT17-1 -> 0.011712531 | AX18: df | AY18: SS | AZ18: MS | BA18: F | BB18: Significance F | BH18: Jan 04, 2026 | BI18: 321.4 | BJ18: 0.0061 | BK18: =BI18/BI17-1 -> 0.0048460216 | BL18: ANOVA
D19: Gopal Snacks | E19: =SLOPE(BK4:BK106,'% Change'!H5:H107) -> 0.96211318 | P19: Dec 28, 2025 | Q19: 5984.5 | R19: -0.008 | S19: =Q19/Q18-1 -> 0.0011710581 | U19: Residual | V19: 100 | W19: 0.089116347 | X19: 0.00089116347 | AE19: Dec 28, 2025 | AF19: 735.6 | AG19: -0.0184 | AH19: =AF19/AF18-1 -> 0.047714001 | AI19: Regression | AJ19: 1 | AK19: 0.030466776 | AL19: 0.030466776 | AM19: 17.479497 | AN19: 6.2343411e-05 | AS19: Dec 28, 2025 | AT19: 471.5 | AU19: 0.111 | AV19: =AT19/AT18-1 -> 0.059907834 | AW19: Regression | AX19: 1 | AY19: 0.02531058 | AZ19: 0.02531058 | BA19: 12.676317 | BB19: 0.00056862658 | BH19: Dec 28, 2025 | BI19: 319.45 | BJ19: 0.0293 | BK19: =BI19/BI18-1 -> -0.006067206 | BM19: df | BN19: SS | BO19: MS | BP19: F | BQ19: Significance F
P20: Dec 21, 2025 | Q20: 6032.5 | R20: -0.0116 | S20: =Q20/Q19-1 -> 0.0080207202 | U20: Total | V20: 101 | W20: 0.09946204 | AE20: Dec 21, 2025 | AF20: 749.4 | AG20: 0.0003 | AH20: =AF20/AF19-1 -> 0.018760196 | AI20: Residual | AJ20: 100 | AK20: 0.17430007 | AL20: 0.0017430007 | AS20: Dec 21, 2025 | AT20: 424.4 | AU20: -0.004 | AV20: =AT20/AT19-1 -> -0.099893955 | AW20: Residual | AX20: 100 | AY20: 0.19966824 | AZ20: 0.0019966824 | BH20: Dec 21, 2025 | BI20: 310.35 | BJ20: -0.0023 | BK20: =BI20/BI19-1 -> -0.028486461 | BL20: Regression | BM20: 1 | BN20: 0.032674019 | BO20: 0.032674019 | BP20: 14.259825 | BQ20: 0.00027044507
P21: Dec 14, 2025 | Q21: 6103 | R21: 0.0317 | S21: =Q21/Q20-1 -> 0.011686697 | AE21: Dec 14, 2025 | AF21: 749.2 | AG21: 0.0274 | AH21: =AF21/AF20-1 -> -0.00026688017 | AI21: Total | AJ21: 101 | AK21: 0.20476685 | AS21: Dec 14, 2025 | AT21: 426.1 | AU21: -0.0007 | AV21: =AT21/AT20-1 -> 0.004005655 | AW21: Total | AX21: 101 | AY21: 0.22497882 | BH21: Dec 14, 2025 | BI21: 311.05 | BJ21: -0.0088 | BK21: =BI21/BI20-1 -> 0.002255518 | BL21: Residual | BM21: 100 | BN21: 0.22913337 | BO21: 0.0022913337
P22: Dec 07, 2025 | Q22: 5915.5 | R22: -0.0076 | S22: =Q22/Q21-1 -> -0.030722595 | V22: Coefficients | W22: Standard Error | X22: t Stat | Y22: P-value | Z22: Lower 95% | AA22: Upper 95% | AB22: Lower 95.0% | AC22: Upper 95.0% | AE22: Dec 07, 2025 | AF22: 729.2 | AG22: 0.0173 | AH22: =AF22/AF21-1 -> -0.026695141 | AS22: Dec 07, 2025 | AT22: 426.4 | AU22: 0.0405 | AV22: =AT22/AT21-1 -> 0.00070406008 | BH22: Dec 07, 2025 | BI22: 313.8 | BJ22: -0.0264 | BK22: =BI22/BI21-1 -> 0.0088410223 | BL22: Total | BM22: 101 | BN22: 0.26180739
P23: Nov 30, 2025 | Q23: 5961 | R23: 0.0197 | S23: =Q23/Q22-1 -> 0.0076916575 | U23: Intercept | V23: -0.0010545032 | W23: 0.0029574007 | X23: -0.35656418 | Y23: 0.72216934 | Z23: -0.006921902 | AA23: 0.0048128957 | AB23: -0.006921902 | AC23: 0.0048128957 | AE23: Nov 30, 2025 | AF23: 716.8 | AG23: -0.0005 | AH23: =AF23/AF22-1 -> -0.017004937 | AJ23: Coefficients | AK23: Standard Error | AL23: t Stat | AM23: P-value | AN23: Lower 95% | AO23: Upper 95% | AP23: Lower 95.0% | AQ23: Upper 95.0% | AS23: Nov 30, 2025 | AT23: 409.8 | AU23: -0.048 | AV23: =AT23/AT22-1 -> -0.038930582 | AX23: Coefficients | AY23: Standard Error | AZ23: t Stat | BA23: P-value | BB23: Lower 95% | BC23: Upper 95% | BD23: Lower 95.0% | BE23: Upper 95.0% | BH23: Nov 30, 2025 | BI23: 322.3 | BJ23: -0.0251 | BK23: =BI23/BI22-1 -> 0.027087317
P24: Nov 23, 2025 | Q24: 5846 | R24: 0.0057 | S24: =Q24/Q23-1 -> -0.019292065 | U24: 0.016414687 | V24: 0.53801786 | W24: 0.15790489 | X24: 3.4072273 | Y24: 0.00094667939 | Z24: 0.22473905 | AA24: 0.85129667 | AB24: 0.22473905 | AC24: 0.85129667 | AE24: Nov 23, 2025 | AF24: 717.15 | AG24: 0.0072 | AH24: =AF24/AF23-1 -> 0.00048828125 | AI24: Intercept | AJ24: -0.00055686406 | AK24: 0.0041359976 | AL24: -0.13463839 | AM24: 0.89316841 | AN24: -0.0087625654 | AO24: 0.0076488373 | AP24: -0.0087625654 | AQ24: 0.0076488373 | AS24: Nov 23, 2025 | AT24: 430.45 | AU24: -0.0244 | AV24: =AT24/AT23-1 -> 0.050390434 | AW24: Intercept | AX24: -0.0022880549 | AY24: 0.0044267601 | AZ24: -0.51686897 | BA24: 0.6063889 | BB24: -0.011070621 | BC24: 0.0064945111 | BD24: -0.011070621 | BE24: 0.0064945111 | BH24: Nov 23, 2025 | BI24: 330.6 | BJ24: -0.0088 | BK24: =BI24/BI23-1 -> 0.025752405 | BM24: Coefficients | BN24: Standard Error | BO24: t Stat | BP24: P-value | BQ24: Lower 95% | BR24: Upper 95% | BS24: Lower 95.0% | BT24: Upper 95.0%
P25: Nov 16, 2025 | Q25: 5813 | R25: 0.0016 | S25: =Q25/Q24-1 -> -0.0056448854 | AE25: Nov 16, 2025 | AF25: 712 | AG25: 0.0001 | AH25: =AF25/AF24-1 -> -0.0071812034 | AI25: 0.016414687 | AJ25: 0.92327303 | AK25: 0.22083387 | AL25: 4.1808488 | AM25: 6.2343411e-05 | AN25: 0.48514492 | AO25: 1.3614011 | AP25: 0.48514492 | AQ25: 1.3614011 | AS25: Nov 16, 2025 | AT25: 441.2 | AU25: -0.0289 | AV25: =AT25/AT24-1 -> 0.024973865 | AW25: 0.016414687 | AX25: 0.8415268 | AY25: 0.23635859 | AZ25: 3.5603816 | BA25: 0.00056862658 | BB25: 0.37259808 | BC25: 1.3104555 | BD25: 0.37259808 | BE25: 1.3104555 | BH25: Nov 16, 2025 | BI25: 333.55 | BJ25: 0.012 | BK25: =BI25/BI24-1 -> 0.00892317 | BL25: Intercept | BM25: 0.002980941 | BN25: 0.0047421541 | BO25: 0.62860483 | BP25: 0.53104099 | BQ25: -0.0064273577 | BR25: 0.01238924 | BS25: -0.0064273577 | BT25: 0.01238924
P26: Nov 09, 2025 | Q26: 5803.5 | R26: -0.0575 | S26: =Q26/Q25-1 -> -0.001634268 | AE26: Nov 09, 2025 | AF26: 711.95 | AG26: -0.0077 | AH26: =AF26/AF25-1 -> -7.0224719e-05 | AS26: Nov 09, 2025 | AT26: 454.35 | AU26: 0.0089 | AV26: =AT26/AT25-1 -> 0.029805077 | BH26: Nov 09, 2025 | BI26: 329.6 | BJ26: -0.0891 | BK26: =BI26/BI25-1 -> -0.011842303 | BL26: 0.016414687 | BM26: 0.95613271 | BN26: 0.25319847 | BO26: 3.7762184 | BP26: 0.00027044507 | BQ26: 0.45379417 | BR26: 1.4584713 | BS26: 0.45379417 | BT26: 1.4584713
P27: Nov 02, 2025 | Q27: 6157.5 | R27: 0.055 | S27: =Q27/Q26-1 -> 0.060997674 | T27: Slope | U27: =SLOPE(S4:S106,'% Change'!H5:H107) -> 0.53478667 | AE27: Nov 02, 2025 | AF27: 717.45 | AG27: -0.018 | AH27: =AF27/AF26-1 -> 0.0077252616 | AS27: Nov 02, 2025 | AT27: 450.35 | AU27: -0.0551 | AV27: =AT27/AT26-1 -> -0.0088037856 | AX27: Slope | AY27: =SLOPE(AV4:AV106,'% Change'!H5:H107) -> 0.84414186 | BH27: Nov 02, 2025 | BI27: 361.85 | BJ27: 0.03 | BK27: =BI27/BI26-1 -> 0.097845874
P28: Oct 26, 2025 | Q28: 5836.5 | R28: -0.0358 | S28: =Q28/Q27-1 -> -0.052131547 | AE28: Oct 26, 2025 | AF28: 730.6 | AG28: -0.0028 | AH28: =AF28/AF27-1 -> 0.018328803 | AJ28: Slope | AK28: =SLOPE(AH4:AH106,'% Change'!H5:H107) -> 0.91697348 | AS28: Oct 26, 2025 | AT28: 476.6 | AU28: -0.0171 | AV28: =AT28/AT27-1 -> 0.058287998 | BH28: Oct 26, 2025 | BI28: 351.3 | BJ28: 0.0169 | BK28: =BI28/BI27-1 -> -0.029155728
P29: Oct 19, 2025 | Q29: 6053 | R29: -0.0049 | S29: =Q29/Q28-1 -> 0.037094149 | AE29: Oct 19, 2025 | AF29: 732.65 | AG29: -0.0021 | AH29: =AF29/AF28-1 -> 0.0028059129 | AS29: Oct 19, 2025 | AT29: 484.9 | AU29: 0.0521 | AV29: =AT29/AT28-1 -> 0.017415023 | BH29: Oct 19, 2025 | BI29: 345.45 | BJ29: -0.0116 | BK29: =BI29/BI28-1 -> -0.016652434 | BM29: Slope | BN29: =SLOPE(BK4:BK106,'% Change'!H5:H107) -> 0.96211318
P30: Oct 12, 2025 | Q30: 6083 | R30: 0.036 | S30: =Q30/Q29-1 -> 0.0049562201 | AE30: Oct 12, 2025 | AF30: 734.2 | AG30: 0.0069 | AH30: =AF30/AF29-1 -> 0.0021156077 | AS30: Oct 12, 2025 | AT30: 460.9 | AU30: 0.0107 | AV30: =AT30/AT29-1 -> -0.049494741 | BH30: Oct 12, 2025 | BI30: 349.5 | BJ30: 0.0045 | BK30: =BI30/BI29-1 -> 0.011723838
P31: Oct 05, 2025 | Q31: 5871.5 | R31: -0.0202 | S31: =Q31/Q30-1 -> -0.034769028 | AE31: Oct 05, 2025 | AF31: 729.2 | AG31: -0.0001 | AH31: =AF31/AF30-1 -> -0.0068101335 | AS31: Oct 05, 2025 | AT31: 456 | AU31: -0.0182 | AV31: =AT31/AT30-1 -> -0.010631373 | BH31: Oct 05, 2025 | BI31: 347.95 | BJ31: -0.0024 | BK31: =BI31/BI30-1 -> -0.004434907
P32: Sep 28, 2025 | Q32: 5992.5 | R32: 0.0122 | S32: =Q32/Q31-1 -> 0.020608022 | AE32: Sep 28, 2025 | AF32: 729.25 | AG32: -0.0026 | AH32: =AF32/AF31-1 -> 6.8568294e-05 | AS32: Sep 28, 2025 | AT32: 464.45 | AU32: -0.037 | AV32: =AT32/AT31-1 -> 0.018530702 | BH32: Sep 28, 2025 | BI32: 348.8 | BJ32: -0.0373 | BK32: =BI32/BI31-1 -> 0.0024428797
P33: Sep 21, 2025 | Q33: 5920.5 | R33: -0.0245 | S33: =Q33/Q32-1 -> -0.012015019 | AE33: Sep 21, 2025 | AF33: 731.15 | AG33: -0.0724 | AH33: =AF33/AF32-1 -> 0.0026054165 | AS33: Sep 21, 2025 | AT33: 482.3 | AU33: -0.0651 | AV33: =AT33/AT32-1 -> 0.038432555 | BH33: Sep 21, 2025 | BI33: 362.3 | BJ33: -0.0341 | BK33: =BI33/BI32-1 -> 0.038704128
P34: Sep 14, 2025 | Q34: 6069.5 | R34: -0.0284 | S34: =Q34/Q33-1 -> 0.025166793 | AE34: Sep 14, 2025 | AF34: 788.25 | AG34: 0.0155 | AH34: =AF34/AF33-1 -> 0.07809615 | AS34: Sep 14, 2025 | AT34: 515.9 | AU34: 0.0168 | AV34: =AT34/AT33-1 -> 0.069666183 | BH34: Sep 14, 2025 | BI34: 375.1 | BJ34: 0.0058 | BK34: =BI34/BI33-1 -> 0.035329837
P35: Sep 07, 2025 | Q35: 6247 | R35: 0.0281 | S35: =Q35/Q34-1 -> 0.029244584 | AE35: Sep 07, 2025 | AF35: 776.25 | AG35: -0.0297 | AH35: =AF35/AF34-1 -> -0.015223597 | AS35: Sep 07, 2025 | AT35: 507.4 | AU35: 0.0454 | AV35: =AT35/AT34-1 -> -0.016476061 | BH35: Sep 07, 2025 | BI35: 372.95 | BJ35: 0.0287 | BK35: =BI35/BI34-1 -> -0.0057318049
P36: Aug 31, 2025 | Q36: 6076 | R36: 0.0433 | S36: =Q36/Q35-1 -> -0.027373139 | AE36: Aug 31, 2025 | AF36: 800.05 | AG36: 0.0123 | AH36: =AF36/AF35-1 -> 0.030660225 | AS36: Aug 31, 2025 | AT36: 485.38 | AU36: 0.2022 | AV36: =AT36/AT35-1 -> -0.043397714 | BH36: Aug 31, 2025 | BI36: 362.55 | BJ36: -0.0152 | BK36: =BI36/BI35-1 -> -0.027885776
P37: Aug 24, 2025 | Q37: 5824 | R37: 0.0502 | S37: =Q37/Q36-1 -> -0.041474654 | AE37: Aug 24, 2025 | AF37: 790.3 | AG37: 0.0262 | AH37: =AF37/AF36-1 -> -0.012186738 | AS37: Aug 24, 2025 | AT37: 403.74 | AU37: 0.0102 | AV37: =AT37/AT36-1 -> -0.16819811 | BH37: Aug 24, 2025 | BI37: 368.15 | BJ37: 0.0156 | BK37: =BI37/BI36-1 -> 0.015446145
P38: Aug 17, 2025 | Q38: 5545.5 | R38: 0.0458 | S38: =Q38/Q37-1 -> -0.047819368 | AE38: Aug 17, 2025 | AF38: 770.15 | AG38: 0.0664 | AH38: =AF38/AF37-1 -> -0.025496647 | AS38: Aug 17, 2025 | AT38: 399.66 | AU38: 0.0355 | AV38: =AT38/AT37-1 -> -0.010105513 | BH38: Aug 17, 2025 | BI38: 362.5 | BJ38: 0.0057 | BK38: =BI38/BI37-1 -> -0.015347005
P39: Aug 10, 2025 | Q39: 5302.5 | R39: -0.0157 | S39: =Q39/Q38-1 -> -0.043819313 | AE39: Aug 10, 2025 | AF39: 722.2 | AG39: -0.0008 | AH39: =AF39/AF38-1 -> -0.062260599 | AS39: Aug 10, 2025 | AT39: 385.96 | AU39: -0.0035 | AV39: =AT39/AT38-1 -> -0.034279137 | BH39: Aug 10, 2025 | BI39: 360.45 | BJ39: 0.0215 | BK39: =BI39/BI38-1 -> -0.0056551724
P40: Aug 03, 2025 | Q40: 5387 | R40: -0.0709 | S40: =Q40/Q39-1 -> 0.015935879 | AE40: Aug 03, 2025 | AF40: 722.75 | AG40: -0.0423 | AH40: =AF40/AF39-1 -> 0.00076156189 | AS40: Aug 03, 2025 | AT40: 387.3 | AU40: -0.0617 | AV40: =AT40/AT39-1 -> 0.0034718624 | BH40: Aug 03, 2025 | BI40: 352.85 | BJ40: -0.0226 | BK40: =BI40/BI39-1 -> -0.021084755
P41: Jul 27, 2025 | Q41: 5798 | R41: 0.0365 | S41: =Q41/Q40-1 -> 0.076294784 | AE41: Jul 27, 2025 | AF41: 754.65 | AG41: -0.0225 | AH41: =AF41/AF40-1 -> 0.044136977 | AS41: Jul 27, 2025 | AT41: 412.76 | AU41: -0.0185 | AV41: =AT41/AT40-1 -> 0.065737155 | BH41: Jul 27, 2025 | BI41: 361 | BJ41: 0.0625 | BK41: =BI41/BI40-1 -> 0.023097634
... P106: Apr 28, 2024 | Q106: 4744.6 | R106: -0.0116 | S106: =Q106/Q105-1 -> -0.063590432 | AE106: Apr 28, 2024 | AF106: 530.6 | AG106: 0.006 | AH106: =AF106/AF105-1 -> 0.0092249168 | AS106: Apr 28, 2024 | AT106: 334.1 | AU106: 0.0006 | AV106: =AT106/AT105-1 -> -0.023984108 | BH106: Apr 28, 2024 | BI106: 317.65 | BJ106: 0.0017 | BK106: =BI106/BI105-1 -> -0.038007268
AE137: The opening price for Bikaji Foods International today was 684.10.

Sheet Beta - comps
B2: Weighted Average Cost of Capital
B4: All figure are in INR unless otherwise started tax
B6: Peer Comps.
B8: Name of the Company | D8: Country | E8: Total Debt | F8: Total Equity | G8: Tax Rate | H8: Debt / Equity | I8: Debt / Capital | J8: Levered Beta | K8: Unlevered Beta
B10: Nestle India | D10: India | E10: =#REF! -> #REF! | F10: =#REF! -> #REF! | G10: 0.3 | H10: =E10/F10 -> #REF! | I10: =E10/SUM(E10:F10) -> #REF! | J10: =IFERROR('Beta-Regression'!E15,0) -> 0.75565254 | K10: =J10/(1+(1-G10)*H10) -> #REF!
B11: Britannia Inds. | D11: India | E11: =#REF! -> #REF! | F11: =#REF! -> #REF! | G11: 0.3 | H11: =E11/F11 -> #REF! | I11: =E11/SUM(E11:F11) -> #REF! | J11: =IFERROR('Beta-Regression'!E16,0) -> 0.53478667 | K11: =J11/(1+(1-G11)*H11) -> #REF!
B12: Bikaji Foods | D12: India | E12: =#REF! -> #REF! | F12: =#REF! -> #REF! | G12: 0.3 | H12: =E12/F12 -> #REF! | I12: =E12/SUM(E12:F12) -> #REF! | J12: =IFERROR('Beta-Regression'!E17,0) -> 0.91697348 | K12: =J12/(1+(1-G12)*H12) -> #REF!
B13: Zydus Wellness | D13: India | E13: =#REF! -> #REF! | F13: =#REF! -> #REF! | G13: 0.3 | H13: =E13/F13 -> #REF! | I13: =E13/SUM(E13:F13) -> #REF! | J13: =IFERROR('Beta-Regression'!E18,0) -> 0.84414186 | K13: =J13/(1+(1-G13)*H13) -> #REF!
B14: The Bombay Burmah | D14: India | E14: =#REF! -> #REF! | F14: =#REF! -> #REF! | G14: 0.3 | H14: =E14/F14 -> #REF! | I14: =E14/SUM(E14:F14) -> #REF! | J14: 0 | K14: =J14/(1+(1-G14)*H14) -> #REF!
B15: Mrs Bectors | D15: India | E15: =#REF! -> #REF! | F15: =#REF! -> #REF! | G15: 0.3 | H15: =E15/F15 -> #REF! | I15: =E15/SUM(E15:F15) -> #REF! | J15: 0 | K15: =J15/(1+(1-G15)*H15) -> #REF!
B16: Gopal Snacks | D16: India | E16: =#REF! -> #REF! | F16: =#REF! -> #REF! | G16: 0.3 | H16: =E16/F16 -> #REF! | I16: =E16/SUM(E16:F16) -> #REF! | J16: =IFERROR('Beta-Regression'!E19,0) -> 0.96211318 | K16: =J16/(1+(1-G16)*H16) -> #REF!
F18: Average | G18: =AVERAGE(G10:G16) -> 0.3 | H18: =AVERAGE(H10:H16) -> #REF! | I18: =AVERAGE(I10:I16) -> #REF! | J18: =AVERAGE(J10:J16) -> 0.5733811 | K18: =AVERAGE(K10:K16) -> #REF!
F19: Median | G19: =MEDIAN(G10:G16) -> 0.3 | H19: =MEDIAN(H10:H16) -> #REF! | I19: =MEDIAN(I10:I16) -> #REF! | J19: =MEDIAN(J10:J16) -> 0.75565254 | K19: =MEDIAN(K10:K16) -> #REF!
B23: Cost of Debt | G23: Cost of Equity
G24: Risk free rate | J24: 0.0717
B25: Pre-tax Cost of Debt | D25: =2196/444 -> 4.9459459 | G25: Equity Risk Premium | J25: ='% Change'!J9-'Beta - comps'!J24 -> -0.0580875
B26: Tax Rate | D26: 0.3 | G26: Leveraged Beta | J26: =J10 -> 0.75565254
B27: Profit Tax Cost of Debt | D27: =D25*(1-D26) -> 3.4621622 | G27: Coat of Equity | J27: =J24+J25*J26 -> 0.027806033
B30: Capital Structure | G30: Cost of Equity
D32: Current | E32: Target | G32: Comps Median Unlevered Beta | J32: =K19 -> #REF!
B33: Total Debt | C33: =E10 -> #REF! | D33: =C33/$C$35 -> #REF! | E33: =J18 -> 0.5733811 | G33: Target. Debt/Equity | J33: =E37 -> #REF!
B34: Market Capitalization | C34: =F10 -> #REF! | D34: =C34/$C$35 -> #REF! | E34: =E35-E33 -> #REF! | G34: Tax Rate | J34: =D26 -> 0.3
B35: Total Capital | C35: =SUM(C33:C34) -> #REF! | D35: =C35/$C$35 -> #REF! | E35: =D35 -> #REF! | G35: Levered Beta | J35: =J32*(1=(1-J34)*J33) -> #REF!
B37: Debt /Equity | D37: =D33/D34 -> #REF! | E37: =E33/E34 -> #REF!
G38: Weighted Average Cost of Capital
I40: Total cost | J40: total weight
G41: Debt | I41: =D27 -> 3.4621622 | J41: =E33 -> 0.5733811
G42: Equity | I42: =J27 -> 0.027806033 | J42: =E34 -> #REF!
G43: Weighted Average cost of Capital | J43: =SUMPRODUCT(I41:I42,J41:J42) -> #REF!

Sheet Sheet1
